[{"id_colonia":790,"colonia_place_count":2,"colonia_avg_rating":4.4,"colonia_avg_traffic":499.0},{"id_colonia":2850,"colonia_place_count":1,"colonia_avg_rating":3.9,"colonia_avg_traffic":32.0},{"id_colonia":2468,"colonia_place_count":1,"colonia_avg_rating":4.0,"colonia_avg_traffic":1409.0},{"id_colonia":1798,"colonia_place_count":23,"colonia_avg_rating":4.37,"colonia_avg_traffic":63.0},{"id_colonia":2429,"colonia_place_count":1,"colonia_avg_rating":2.0,"colonia_avg_traffic":2.0},{"id_colonia":652,"colonia_place_count":2,"colonia_avg_rating":3.9,"colonia_avg_traffic":195.0},{"id_colonia":70,"colonia_place_count":1,"colonia_avg_rating":4.5,"colonia_avg_traffic":2590.0},{"id_colonia":3726,"colonia_place_count":2,"colonia_avg_rating":4.4,"colonia_avg_traffic":78.0},{"id_colonia":1075,"colonia_place_count":1,"colonia_avg_rating":4.4,"colonia_avg_traffic":199.0},{"id_colonia":350,"colonia_place_count":1,"colonia_avg_rating":4.6,"colonia_avg_traffic":318.0},{"id_colonia":1128,"colonia_place_count":6,"colonia_avg_rating":4.1,"colonia_avg_traffic":1101.0},{"id_colonia":2425,"colonia_place_count":15,"colonia_avg_rating":4.5,"colonia_avg_traffic":9.0},{"id_colonia":1284,"colonia_place_count":1,"colonia_avg_rating":4.7,"colonia_avg_traffic":6.0},{"id_colonia":2614,"colonia_place_count":24,"colonia_avg_rating":4.17,"colonia_avg_traffic":1614.0},{"id_colonia":2520,"colonia_place_count":34,"colonia_avg_rating":4.31,"colonia_avg_traffic":6396.0},{"id_colonia":2299,"colonia_place_count":31,"colonia_avg_rating":4.06,"colonia_avg_traffic":57.0},{"id_colonia":3658,"colonia_place_count":27,"colonia_avg_rating":4.6,"colonia_avg_traffic":13.0},{"id_colonia":663,"colonia_place_count":2,"colonia_avg_rating":3.7,"colonia_avg_traffic":52.0},{"id_colonia":1307,"colonia_place_count":1,"colonia_avg_rating":4.3,"colonia_avg_traffic":10.0},{"id_colonia":3793,"colonia_place_count":1,"colonia_avg_rating":4.0,"colonia_avg_traffic":108.0},{"id_colonia":1493,"colonia_place_count":1,"colonia_avg_rating":4.0,"colonia_avg_traffic":242.0},{"id_colonia":3725,"colonia_place_count":2,"colonia_avg_rating":4.6,"colonia_avg_traffic":4.0},{"id_colonia":2740,"colonia_place_count":1,"colonia_avg_rating":4.3,"colonia_avg_traffic":161.0},{"id_colonia":1373,"colonia_place_count":7,"colonia_avg_rating":4.24,"colonia_avg_traffic":1694.0},{"id_colonia":2686,"colonia_place_count":1,"colonia_avg_rating":4.7,"colonia_avg_traffic":14.0},{"id_colonia":1830,"colonia_place_count":3,"colonia_avg_rating":3.1,"colonia_avg_traffic":47.0},{"id_colonia":173,"colonia_place_count":6,"colonia_avg_rating":4.33,"colonia_avg_traffic":145.0},{"id_colonia":1018,"colonia_place_count":1,"colonia_avg_rating":3.6,"colonia_avg_traffic":14.0},{"id_colonia":2152,"colonia_place_count":1,"colonia_avg_rating":2.9,"colonia_avg_traffic":18.0},{"id_colonia":2276,"colonia_place_count":2,"colonia_avg_rating":4.3,"colonia_avg_traffic":13.0},{"id_colonia":42,"colonia_place_count":9,"colonia_avg_rating":3.74,"colonia_avg_traffic":277.0},{"id_colonia":1742,"colonia_place_count":1,"colonia_avg_rating":4.9,"colonia_avg_traffic":7.0},{"id_colonia":3211,"colonia_place_count":25,"colonia_avg_rating":3.85,"colonia_avg_traffic":294.0},{"id_colonia":1682,"colonia_place_count":1,"colonia_avg_rating":4.8,"colonia_avg_traffic":14.0},{"id_colonia":1431,"colonia_place_count":10,"colonia_avg_rating":4.21,"colonia_avg_traffic":515.0},{"id_colonia":1595,"colonia_place_count":1,"colonia_avg_rating":4.6,"colonia_avg_traffic":13.0},{"id_colonia":658,"colonia_place_count":1,"colonia_avg_rating":3.7,"colonia_avg_traffic":3.0},{"id_colonia":815,"colonia_place_count":13,"colonia_avg_rating":4.18,"colonia_avg_traffic":55.0},{"id_colonia":2259,"colonia_place_count":2,"colonia_avg_rating":4.7,"colonia_avg_traffic":250.0},{"id_colonia":3521,"colonia_place_count":1,"colonia_avg_rating":5.0,"colonia_avg_traffic":1.0},{"id_colonia":440,"colonia_place_count":1,"colonia_avg_rating":4.7,"colonia_avg_traffic":3.0},{"id_colonia":2054,"colonia_place_count":1,"colonia_avg_rating":3.8,"colonia_avg_traffic":43.0},{"id_colonia":3150,"colonia_place_count":53,"colonia_avg_rating":4.3,"colonia_avg_traffic":90.0},{"id_colonia":794,"colonia_place_count":10,"colonia_avg_rating":4.21,"colonia_avg_traffic":2485.0},{"id_colonia":19,"colonia_place_count":1,"colonia_avg_rating":4.0,"colonia_avg_traffic":63.0},{"id_colonia":1510,"colonia_place_count":1,"colonia_avg_rating":4.4,"colonia_avg_traffic":569.0},{"id_colonia":3700,"colonia_place_count":301,"colonia_avg_rating":4.01,"colonia_avg_traffic":318.0},{"id_colonia":1368,"colonia_place_count":3,"colonia_avg_rating":4.07,"colonia_avg_traffic":2475.0},{"id_colonia":357,"colonia_place_count":1,"colonia_avg_rating":4.2,"colonia_avg_traffic":12.0},{"id_colonia":3373,"colonia_place_count":2,"colonia_avg_rating":3.75,"colonia_avg_traffic":600.0},{"id_colonia":3277,"colonia_place_count":1,"colonia_avg_rating":5.0,"colonia_avg_traffic":1.0},{"id_colonia":366,"colonia_place_count":1,"colonia_avg_rating":4.8,"colonia_avg_traffic":522.0},{"id_colonia":307,"colonia_place_count":1,"colonia_avg_rating":4.1,"colonia_avg_traffic":2073.0},{"id_colonia":3639,"colonia_place_count":1,"colonia_avg_rating":4.9,"colonia_avg_traffic":47.0},{"id_colonia":1644,"colonia_place_count":1,"colonia_avg_rating":4.5,"colonia_avg_traffic":54.0},{"id_colonia":1614,"colonia_place_count":1,"colonia_avg_rating":4.4,"colonia_avg_traffic":29.0},{"id_colonia":1239,"colonia_place_count":11,"colonia_avg_rating":4.2,"colonia_avg_traffic":2643.0},{"id_colonia":3811,"colonia_place_count":3,"colonia_avg_rating":4.17,"colonia_avg_traffic":209.0},{"id_colonia":54,"colonia_place_count":5,"colonia_avg_rating":4.38,"colonia_avg_traffic":7.0},{"id_colonia":743,"colonia_place_count":1,"colonia_avg_rating":5.0,"colonia_avg_traffic":8.0},{"id_colonia":1484,"colonia_place_count":15,"colonia_avg_rating":4.08,"colonia_avg_traffic":5454.0},{"id_colonia":10,"colonia_place_count":9,"colonia_avg_rating":4.04,"colonia_avg_traffic":3965.0},{"id_colonia":1940,"colonia_place_count":5,"colonia_avg_rating":4.14,"colonia_avg_traffic":1874.0},{"id_colonia":2576,"colonia_place_count":3,"colonia_avg_rating":4.43,"colonia_avg_traffic":1418.0},{"id_colonia":3068,"colonia_place_count":2,"colonia_avg_rating":3.75,"colonia_avg_traffic":128.0},{"id_colonia":1602,"colonia_place_count":9,"colonia_avg_rating":4.16,"colonia_avg_traffic":19.0},{"id_colonia":1278,"colonia_place_count":4,"colonia_avg_rating":4.45,"colonia_avg_traffic":3.0},{"id_colonia":3591,"colonia_place_count":7,"colonia_avg_rating":4.56,"colonia_avg_traffic":3528.0},{"id_colonia":3673,"colonia_place_count":2,"colonia_avg_rating":4.0,"colonia_avg_traffic":2.0},{"id_colonia":596,"colonia_place_count":58,"colonia_avg_rating":3.89,"colonia_avg_traffic":224.0},{"id_colonia":1880,"colonia_place_count":4,"colonia_avg_rating":3.98,"colonia_avg_traffic":282.0},{"id_colonia":50,"colonia_place_count":26,"colonia_avg_rating":3.85,"colonia_avg_traffic":583.0},{"id_colonia":3732,"colonia_place_count":69,"colonia_avg_rating":4.02,"colonia_avg_traffic":183.0},{"id_colonia":3301,"colonia_place_count":1,"colonia_avg_rating":4.2,"colonia_avg_traffic":114.0},{"id_colonia":3190,"colonia_place_count":1,"colonia_avg_rating":4.2,"colonia_avg_traffic":14633.0},{"id_colonia":1266,"colonia_place_count":1,"colonia_avg_rating":3.8,"colonia_avg_traffic":5.0},{"id_colonia":1104,"colonia_place_count":1,"colonia_avg_rating":4.5,"colonia_avg_traffic":39.0},{"id_colonia":2,"colonia_place_count":117,"colonia_avg_rating":4.07,"colonia_avg_traffic":525.0},{"id_colonia":75,"colonia_place_count":1,"colonia_avg_rating":3.9,"colonia_avg_traffic":98.0},{"id_colonia":2183,"colonia_place_count":5,"colonia_avg_rating":3.36,"colonia_avg_traffic":158.0},{"id_colonia":1942,"colonia_place_count":9,"colonia_avg_rating":4.42,"colonia_avg_traffic":5.0},{"id_colonia":714,"colonia_place_count":50,"colonia_avg_rating":4.51,"colonia_avg_traffic":44.0},{"id_colonia":2397,"colonia_place_count":2,"colonia_avg_rating":4.4,"colonia_avg_traffic":32.0},{"id_colonia":1920,"colonia_place_count":1,"colonia_avg_rating":4.1,"colonia_avg_traffic":42.0},{"id_colonia":1321,"colonia_place_count":5,"colonia_avg_rating":4.08,"colonia_avg_traffic":44.0},{"id_colonia":3287,"colonia_place_count":6,"colonia_avg_rating":4.15,"colonia_avg_traffic":2433.0},{"id_colonia":2140,"colonia_place_count":6,"colonia_avg_rating":3.87,"colonia_avg_traffic":309.0},{"id_colonia":1786,"colonia_place_count":114,"colonia_avg_rating":4.52,"colonia_avg_traffic":91.0},{"id_colonia":1403,"colonia_place_count":2,"colonia_avg_rating":4.55,"colonia_avg_traffic":301.0},{"id_colonia":3755,"colonia_place_count":3,"colonia_avg_rating":4.8,"colonia_avg_traffic":6.0},{"id_colonia":1006,"colonia_place_count":5,"colonia_avg_rating":3.86,"colonia_avg_traffic":8.0},{"id_colonia":1008,"colonia_place_count":3,"colonia_avg_rating":3.47,"colonia_avg_traffic":40.0},{"id_colonia":2683,"colonia_place_count":190,"colonia_avg_rating":4.16,"colonia_avg_traffic":106.0},{"id_colonia":2791,"colonia_place_count":2,"colonia_avg_rating":5.0,"colonia_avg_traffic":1.0},{"id_colonia":2333,"colonia_place_count":2,"colonia_avg_rating":3.3,"colonia_avg_traffic":4.0},{"id_colonia":2035,"colonia_place_count":1,"colonia_avg_rating":4.7,"colonia_avg_traffic":98.0},{"id_colonia":2920,"colonia_place_count":1,"colonia_avg_rating":1.0,"colonia_avg_traffic":1.0},{"id_colonia":750,"colonia_place_count":1,"colonia_avg_rating":3.6,"colonia_avg_traffic":43.0},{"id_colonia":1679,"colonia_place_count":2,"colonia_avg_rating":4.55,"colonia_avg_traffic":18.0},{"id_colonia":977,"colonia_place_count":3,"colonia_avg_rating":2.73,"colonia_avg_traffic":941.0},{"id_colonia":1507,"colonia_place_count":1,"colonia_avg_rating":4.5,"colonia_avg_traffic":77.0},{"id_colonia":3422,"colonia_place_count":1,"colonia_avg_rating":3.9,"colonia_avg_traffic":25.0},{"id_colonia":27,"colonia_place_count":1,"colonia_avg_rating":4.2,"colonia_avg_traffic":5.0},{"id_colonia":2733,"colonia_place_count":11,"colonia_avg_rating":4.58,"colonia_avg_traffic":46.0},{"id_colonia":496,"colonia_place_count":1,"colonia_avg_rating":3.8,"colonia_avg_traffic":24.0},{"id_colonia":2752,"colonia_place_count":1,"colonia_avg_rating":5.0,"colonia_avg_traffic":1.0},{"id_colonia":2803,"colonia_place_count":9,"colonia_avg_rating":4.18,"colonia_avg_traffic":67.0},{"id_colonia":667,"colonia_place_count":1,"colonia_avg_rating":5.0,"colonia_avg_traffic":1.0},{"id_colonia":814,"colonia_place_count":3,"colonia_avg_rating":3.07,"colonia_avg_traffic":2.0},{"id_colonia":3602,"colonia_place_count":1,"colonia_avg_rating":4.5,"colonia_avg_traffic":31.0},{"id_colonia":1800,"colonia_place_count":10,"colonia_avg_rating":4.38,"colonia_avg_traffic":12.0},{"id_colonia":926,"colonia_place_count":1,"colonia_avg_rating":2.0,"colonia_avg_traffic":1.0},{"id_colonia":1009,"colonia_place_count":1,"colonia_avg_rating":3.5,"colonia_avg_traffic":16.0},{"id_colonia":607,"colonia_place_count":2,"colonia_avg_rating":4.15,"colonia_avg_traffic":6569.0},{"id_colonia":1546,"colonia_place_count":1,"colonia_avg_rating":4.7,"colonia_avg_traffic":174.0},{"id_colonia":3717,"colonia_place_count":6,"colonia_avg_rating":4.42,"colonia_avg_traffic":12.0},{"id_colonia":1836,"colonia_place_count":198,"colonia_avg_rating":4.25,"colonia_avg_traffic":60.0},{"id_colonia":1788,"colonia_place_count":2,"colonia_avg_rating":4.25,"colonia_avg_traffic":37.0},{"id_colonia":3500,"colonia_place_count":1,"colonia_avg_rating":5.0,"colonia_avg_traffic":1.0},{"id_colonia":3651,"colonia_place_count":2,"colonia_avg_rating":3.9,"colonia_avg_traffic":79.0},{"id_colonia":3570,"colonia_place_count":5,"colonia_avg_rating":4.62,"colonia_avg_traffic":41.0},{"id_colonia":1062,"colonia_place_count":1,"colonia_avg_rating":3.2,"colonia_avg_traffic":164.0},{"id_colonia":115,"colonia_place_count":1,"colonia_avg_rating":4.2,"colonia_avg_traffic":416.0},{"id_colonia":1823,"colonia_place_count":1,"colonia_avg_rating":4.5,"colonia_avg_traffic":29.0},{"id_colonia":1848,"colonia_place_count":15,"colonia_avg_rating":4.31,"colonia_avg_traffic":307.0},{"id_colonia":1862,"colonia_place_count":25,"colonia_avg_rating":4.49,"colonia_avg_traffic":16627.0},{"id_colonia":2925,"colonia_place_count":1,"colonia_avg_rating":2.7,"colonia_avg_traffic":6.0},{"id_colonia":3034,"colonia_place_count":35,"colonia_avg_rating":3.85,"colonia_avg_traffic":669.0},{"id_colonia":2401,"colonia_place_count":36,"colonia_avg_rating":4.08,"colonia_avg_traffic":15.0},{"id_colonia":1285,"colonia_place_count":5,"colonia_avg_rating":4.72,"colonia_avg_traffic":71.0},{"id_colonia":3054,"colonia_place_count":26,"colonia_avg_rating":4.35,"colonia_avg_traffic":372.0},{"id_colonia":3728,"colonia_place_count":16,"colonia_avg_rating":4.41,"colonia_avg_traffic":205.0},{"id_colonia":3404,"colonia_place_count":1,"colonia_avg_rating":4.8,"colonia_avg_traffic":26.0},{"id_colonia":3523,"colonia_place_count":2,"colonia_avg_rating":3.75,"colonia_avg_traffic":5.0},{"id_colonia":1924,"colonia_place_count":6,"colonia_avg_rating":4.08,"colonia_avg_traffic":109.0},{"id_colonia":816,"colonia_place_count":1,"colonia_avg_rating":5.0,"colonia_avg_traffic":2.0},{"id_colonia":2598,"colonia_place_count":1,"colonia_avg_rating":4.4,"colonia_avg_traffic":56.0},{"id_colonia":676,"colonia_place_count":1,"colonia_avg_rating":5.0,"colonia_avg_traffic":4.0},{"id_colonia":153,"colonia_place_count":2,"colonia_avg_rating":4.4,"colonia_avg_traffic":5.0},{"id_colonia":2951,"colonia_place_count":1,"colonia_avg_rating":3.2,"colonia_avg_traffic":9.0},{"id_colonia":2601,"colonia_place_count":1,"colonia_avg_rating":4.9,"colonia_avg_traffic":27.0},{"id_colonia":1753,"colonia_place_count":1,"colonia_avg_rating":3.7,"colonia_avg_traffic":3.0},{"id_colonia":3526,"colonia_place_count":1,"colonia_avg_rating":5.0,"colonia_avg_traffic":2.0},{"id_colonia":2760,"colonia_place_count":6,"colonia_avg_rating":3.58,"colonia_avg_traffic":56.0},{"id_colonia":259,"colonia_place_count":1,"colonia_avg_rating":4.4,"colonia_avg_traffic":8531.0},{"id_colonia":3107,"colonia_place_count":7,"colonia_avg_rating":3.9,"colonia_avg_traffic":211.0},{"id_colonia":965,"colonia_place_count":8,"colonia_avg_rating":4.06,"colonia_avg_traffic":52.0},{"id_colonia":3603,"colonia_place_count":1,"colonia_avg_rating":3.9,"colonia_avg_traffic":14.0},{"id_colonia":3660,"colonia_place_count":4,"colonia_avg_rating":4.43,"colonia_avg_traffic":2.0},{"id_colonia":2109,"colonia_place_count":1,"colonia_avg_rating":3.8,"colonia_avg_traffic":3311.0},{"id_colonia":1378,"colonia_place_count":5,"colonia_avg_rating":3.54,"colonia_avg_traffic":357.0},{"id_colonia":3,"colonia_place_count":1,"colonia_avg_rating":4.2,"colonia_avg_traffic":502.0},{"id_colonia":2465,"colonia_place_count":10,"colonia_avg_rating":4.31,"colonia_avg_traffic":536.0},{"id_colonia":1923,"colonia_place_count":15,"colonia_avg_rating":4.37,"colonia_avg_traffic":17.0},{"id_colonia":3492,"colonia_place_count":26,"colonia_avg_rating":4.49,"colonia_avg_traffic":6.0},{"id_colonia":249,"colonia_place_count":7,"colonia_avg_rating":4.41,"colonia_avg_traffic":44.0},{"id_colonia":1126,"colonia_place_count":2,"colonia_avg_rating":3.4,"colonia_avg_traffic":614.0},{"id_colonia":3308,"colonia_place_count":1,"colonia_avg_rating":1.8,"colonia_avg_traffic":10.0},{"id_colonia":3178,"colonia_place_count":5,"colonia_avg_rating":3.98,"colonia_avg_traffic":38.0},{"id_colonia":2965,"colonia_place_count":2,"colonia_avg_rating":3.3,"colonia_avg_traffic":1517.0},{"id_colonia":1678,"colonia_place_count":14,"colonia_avg_rating":4.17,"colonia_avg_traffic":50.0},{"id_colonia":34,"colonia_place_count":1,"colonia_avg_rating":4.0,"colonia_avg_traffic":99.0},{"id_colonia":418,"colonia_place_count":1,"colonia_avg_rating":2.9,"colonia_avg_traffic":7.0},{"id_colonia":3099,"colonia_place_count":1,"colonia_avg_rating":3.7,"colonia_avg_traffic":34.0},{"id_colonia":1774,"colonia_place_count":1,"colonia_avg_rating":3.6,"colonia_avg_traffic":9.0},{"id_colonia":1748,"colonia_place_count":191,"colonia_avg_rating":4.25,"colonia_avg_traffic":47.0},{"id_colonia":761,"colonia_place_count":2,"colonia_avg_rating":4.6,"colonia_avg_traffic":54.0},{"id_colonia":972,"colonia_place_count":37,"colonia_avg_rating":3.98,"colonia_avg_traffic":251.0},{"id_colonia":2864,"colonia_place_count":2,"colonia_avg_rating":4.35,"colonia_avg_traffic":979.0},{"id_colonia":1681,"colonia_place_count":2,"colonia_avg_rating":3.65,"colonia_avg_traffic":2.0},{"id_colonia":904,"colonia_place_count":2,"colonia_avg_rating":4.4,"colonia_avg_traffic":104.0},{"id_colonia":3111,"colonia_place_count":1,"colonia_avg_rating":4.7,"colonia_avg_traffic":41.0},{"id_colonia":3682,"colonia_place_count":14,"colonia_avg_rating":3.88,"colonia_avg_traffic":23.0},{"id_colonia":2900,"colonia_place_count":4,"colonia_avg_rating":4.35,"colonia_avg_traffic":23.0},{"id_colonia":3105,"colonia_place_count":15,"colonia_avg_rating":4.65,"colonia_avg_traffic":6.0},{"id_colonia":39,"colonia_place_count":1,"colonia_avg_rating":3.7,"colonia_avg_traffic":76.0},{"id_colonia":690,"colonia_place_count":5,"colonia_avg_rating":3.54,"colonia_avg_traffic":7.0},{"id_colonia":393,"colonia_place_count":1,"colonia_avg_rating":5.0,"colonia_avg_traffic":2.0},{"id_colonia":2977,"colonia_place_count":14,"colonia_avg_rating":4.09,"colonia_avg_traffic":21.0},{"id_colonia":1569,"colonia_place_count":1,"colonia_avg_rating":4.0,"colonia_avg_traffic":1556.0},{"id_colonia":3705,"colonia_place_count":1,"colonia_avg_rating":4.0,"colonia_avg_traffic":71.0},{"id_colonia":683,"colonia_place_count":1,"colonia_avg_rating":3.7,"colonia_avg_traffic":3064.0},{"id_colonia":3571,"colonia_place_count":8,"colonia_avg_rating":3.95,"colonia_avg_traffic":8.0},{"id_colonia":1265,"colonia_place_count":3,"colonia_avg_rating":4.33,"colonia_avg_traffic":9039.0},{"id_colonia":1793,"colonia_place_count":4,"colonia_avg_rating":4.15,"colonia_avg_traffic":10.0},{"id_colonia":2726,"colonia_place_count":24,"colonia_avg_rating":4.23,"colonia_avg_traffic":463.0},{"id_colonia":1048,"colonia_place_count":1,"colonia_avg_rating":4.5,"colonia_avg_traffic":2485.0},{"id_colonia":99,"colonia_place_count":9,"colonia_avg_rating":4.36,"colonia_avg_traffic":13.0},{"id_colonia":2156,"colonia_place_count":2,"colonia_avg_rating":4.15,"colonia_avg_traffic":16.0},{"id_colonia":883,"colonia_place_count":13,"colonia_avg_rating":3.57,"colonia_avg_traffic":101.0},{"id_colonia":726,"colonia_place_count":6,"colonia_avg_rating":4.25,"colonia_avg_traffic":10.0},{"id_colonia":3057,"colonia_place_count":5,"colonia_avg_rating":4.7,"colonia_avg_traffic":37.0},{"id_colonia":1887,"colonia_place_count":6,"colonia_avg_rating":3.03,"colonia_avg_traffic":56.0},{"id_colonia":3525,"colonia_place_count":604,"colonia_avg_rating":4.15,"colonia_avg_traffic":84.0},{"id_colonia":3727,"colonia_place_count":10,"colonia_avg_rating":3.72,"colonia_avg_traffic":9.0},{"id_colonia":3539,"colonia_place_count":8,"colonia_avg_rating":3.85,"colonia_avg_traffic":76.0},{"id_colonia":318,"colonia_place_count":23,"colonia_avg_rating":4.06,"colonia_avg_traffic":286.0},{"id_colonia":3572,"colonia_place_count":3,"colonia_avg_rating":3.73,"colonia_avg_traffic":5.0},{"id_colonia":933,"colonia_place_count":1,"colonia_avg_rating":3.6,"colonia_avg_traffic":119.0},{"id_colonia":2410,"colonia_place_count":4,"colonia_avg_rating":4.63,"colonia_avg_traffic":90.0},{"id_colonia":1296,"colonia_place_count":1,"colonia_avg_rating":3.0,"colonia_avg_traffic":1.0},{"id_colonia":1792,"colonia_place_count":4,"colonia_avg_rating":4.48,"colonia_avg_traffic":148.0},{"id_colonia":1976,"colonia_place_count":1,"colonia_avg_rating":5.0,"colonia_avg_traffic":1.0},{"id_colonia":3750,"colonia_place_count":1,"colonia_avg_rating":5.0,"colonia_avg_traffic":2.0},{"id_colonia":3198,"colonia_place_count":5,"colonia_avg_rating":4.76,"colonia_avg_traffic":30.0},{"id_colonia":1257,"colonia_place_count":15,"colonia_avg_rating":3.97,"colonia_avg_traffic":233.0},{"id_colonia":234,"colonia_place_count":33,"colonia_avg_rating":4.21,"colonia_avg_traffic":21.0},{"id_colonia":474,"colonia_place_count":4,"colonia_avg_rating":4.1,"colonia_avg_traffic":568.0},{"id_colonia":748,"colonia_place_count":1,"colonia_avg_rating":4.5,"colonia_avg_traffic":15.0},{"id_colonia":696,"colonia_place_count":1,"colonia_avg_rating":4.4,"colonia_avg_traffic":16.0},{"id_colonia":2396,"colonia_place_count":3,"colonia_avg_rating":1.93,"colonia_avg_traffic":3.0},{"id_colonia":969,"colonia_place_count":3,"colonia_avg_rating":4.63,"colonia_avg_traffic":897.0},{"id_colonia":3495,"colonia_place_count":1,"colonia_avg_rating":4.4,"colonia_avg_traffic":37.0},{"id_colonia":1910,"colonia_place_count":987,"colonia_avg_rating":4.1,"colonia_avg_traffic":1067.0},{"id_colonia":1700,"colonia_place_count":1,"colonia_avg_rating":1.0,"colonia_avg_traffic":3.0},{"id_colonia":351,"colonia_place_count":3,"colonia_avg_rating":4.83,"colonia_avg_traffic":18.0},{"id_colonia":1791,"colonia_place_count":3,"colonia_avg_rating":3.33,"colonia_avg_traffic":1.0},{"id_colonia":3371,"colonia_place_count":21,"colonia_avg_rating":4.2,"colonia_avg_traffic":914.0},{"id_colonia":2680,"colonia_place_count":69,"colonia_avg_rating":4.32,"colonia_avg_traffic":170.0},{"id_colonia":970,"colonia_place_count":24,"colonia_avg_rating":3.95,"colonia_avg_traffic":422.0},{"id_colonia":2936,"colonia_place_count":1,"colonia_avg_rating":3.7,"colonia_avg_traffic":3.0},{"id_colonia":837,"colonia_place_count":3,"colonia_avg_rating":4.33,"colonia_avg_traffic":23.0},{"id_colonia":2685,"colonia_place_count":1,"colonia_avg_rating":4.4,"colonia_avg_traffic":331.0},{"id_colonia":3583,"colonia_place_count":1,"colonia_avg_rating":4.6,"colonia_avg_traffic":17.0},{"id_colonia":2737,"colonia_place_count":7,"colonia_avg_rating":4.53,"colonia_avg_traffic":63.0},{"id_colonia":2819,"colonia_place_count":8,"colonia_avg_rating":3.86,"colonia_avg_traffic":91.0},{"id_colonia":1627,"colonia_place_count":9,"colonia_avg_rating":3.89,"colonia_avg_traffic":61.0},{"id_colonia":3505,"colonia_place_count":15,"colonia_avg_rating":4.36,"colonia_avg_traffic":19.0},{"id_colonia":2037,"colonia_place_count":1,"colonia_avg_rating":5.0,"colonia_avg_traffic":11.0},{"id_colonia":2053,"colonia_place_count":1,"colonia_avg_rating":4.1,"colonia_avg_traffic":47.0},{"id_colonia":1272,"colonia_place_count":2,"colonia_avg_rating":4.35,"colonia_avg_traffic":11.0},{"id_colonia":1567,"colonia_place_count":2,"colonia_avg_rating":4.15,"colonia_avg_traffic":46.0},{"id_colonia":180,"colonia_place_count":6,"colonia_avg_rating":3.95,"colonia_avg_traffic":661.0},{"id_colonia":626,"colonia_place_count":1,"colonia_avg_rating":4.4,"colonia_avg_traffic":5.0},{"id_colonia":3664,"colonia_place_count":3,"colonia_avg_rating":3.87,"colonia_avg_traffic":155.0},{"id_colonia":1579,"colonia_place_count":7,"colonia_avg_rating":4.04,"colonia_avg_traffic":18.0},{"id_colonia":1571,"colonia_place_count":163,"colonia_avg_rating":4.05,"colonia_avg_traffic":87.0},{"id_colonia":470,"colonia_place_count":17,"colonia_avg_rating":4.08,"colonia_avg_traffic":5049.0},{"id_colonia":1565,"colonia_place_count":149,"colonia_avg_rating":4.02,"colonia_avg_traffic":192.0},{"id_colonia":2018,"colonia_place_count":1,"colonia_avg_rating":4.4,"colonia_avg_traffic":51.0},{"id_colonia":2632,"colonia_place_count":3,"colonia_avg_rating":3.73,"colonia_avg_traffic":1636.0},{"id_colonia":2034,"colonia_place_count":1,"colonia_avg_rating":4.3,"colonia_avg_traffic":17.0},{"id_colonia":1668,"colonia_place_count":27,"colonia_avg_rating":3.98,"colonia_avg_traffic":409.0},{"id_colonia":838,"colonia_place_count":8,"colonia_avg_rating":3.76,"colonia_avg_traffic":118.0},{"id_colonia":2817,"colonia_place_count":1,"colonia_avg_rating":4.0,"colonia_avg_traffic":5.0},{"id_colonia":478,"colonia_place_count":2,"colonia_avg_rating":4.45,"colonia_avg_traffic":64.0},{"id_colonia":1301,"colonia_place_count":2,"colonia_avg_rating":4.75,"colonia_avg_traffic":138.0},{"id_colonia":505,"colonia_place_count":2,"colonia_avg_rating":4.7,"colonia_avg_traffic":1650.0},{"id_colonia":88,"colonia_place_count":3,"colonia_avg_rating":3.47,"colonia_avg_traffic":52.0},{"id_colonia":188,"colonia_place_count":1,"colonia_avg_rating":4.8,"colonia_avg_traffic":13.0},{"id_colonia":3653,"colonia_place_count":1,"colonia_avg_rating":3.2,"colonia_avg_traffic":6.0},{"id_colonia":2768,"colonia_place_count":1,"colonia_avg_rating":4.5,"colonia_avg_traffic":34.0},{"id_colonia":1046,"colonia_place_count":1,"colonia_avg_rating":2.8,"colonia_avg_traffic":69.0},{"id_colonia":2155,"colonia_place_count":3,"colonia_avg_rating":2.93,"colonia_avg_traffic":31.0},{"id_colonia":1328,"colonia_place_count":5,"colonia_avg_rating":3.84,"colonia_avg_traffic":154.0},{"id_colonia":1932,"colonia_place_count":1,"colonia_avg_rating":4.6,"colonia_avg_traffic":18.0},{"id_colonia":2792,"colonia_place_count":5,"colonia_avg_rating":4.38,"colonia_avg_traffic":1895.0},{"id_colonia":210,"colonia_place_count":1,"colonia_avg_rating":5.0,"colonia_avg_traffic":1.0},{"id_colonia":1161,"colonia_place_count":3,"colonia_avg_rating":3.5,"colonia_avg_traffic":14.0},{"id_colonia":447,"colonia_place_count":1,"colonia_avg_rating":5.0,"colonia_avg_traffic":3.0},{"id_colonia":1015,"colonia_place_count":4,"colonia_avg_rating":4.33,"colonia_avg_traffic":306.0},{"id_colonia":3679,"colonia_place_count":370,"colonia_avg_rating":4.09,"colonia_avg_traffic":1983.0},{"id_colonia":3137,"colonia_place_count":1,"colonia_avg_rating":4.3,"colonia_avg_traffic":49.0},{"id_colonia":1944,"colonia_place_count":3,"colonia_avg_rating":4.07,"colonia_avg_traffic":363.0},{"id_colonia":954,"colonia_place_count":2,"colonia_avg_rating":3.85,"colonia_avg_traffic":17.0},{"id_colonia":2455,"colonia_place_count":98,"colonia_avg_rating":4.04,"colonia_avg_traffic":641.0},{"id_colonia":3109,"colonia_place_count":1,"colonia_avg_rating":1.0,"colonia_avg_traffic":1.0},{"id_colonia":1021,"colonia_place_count":11,"colonia_avg_rating":4.45,"colonia_avg_traffic":399.0},{"id_colonia":3753,"colonia_place_count":1,"colonia_avg_rating":4.1,"colonia_avg_traffic":17.0},{"id_colonia":2398,"colonia_place_count":12,"colonia_avg_rating":4.18,"colonia_avg_traffic":23.0},{"id_colonia":3342,"colonia_place_count":7,"colonia_avg_rating":4.13,"colonia_avg_traffic":188.0},{"id_colonia":1247,"colonia_place_count":1,"colonia_avg_rating":5.0,"colonia_avg_traffic":10.0},{"id_colonia":2837,"colonia_place_count":1,"colonia_avg_rating":3.7,"colonia_avg_traffic":3.0},{"id_colonia":2731,"colonia_place_count":1,"colonia_avg_rating":4.6,"colonia_avg_traffic":14.0},{"id_colonia":283,"colonia_place_count":2,"colonia_avg_rating":5.0,"colonia_avg_traffic":8.0},{"id_colonia":686,"colonia_place_count":1,"colonia_avg_rating":3.7,"colonia_avg_traffic":39.0},{"id_colonia":681,"colonia_place_count":1,"colonia_avg_rating":2.6,"colonia_avg_traffic":79.0},{"id_colonia":3573,"colonia_place_count":28,"colonia_avg_rating":4.48,"colonia_avg_traffic":185.0},{"id_colonia":829,"colonia_place_count":1,"colonia_avg_rating":5.0,"colonia_avg_traffic":1.0},{"id_colonia":472,"colonia_place_count":9,"colonia_avg_rating":3.68,"colonia_avg_traffic":232.0},{"id_colonia":444,"colonia_place_count":1,"colonia_avg_rating":4.2,"colonia_avg_traffic":354.0},{"id_colonia":1849,"colonia_place_count":8,"colonia_avg_rating":4.01,"colonia_avg_traffic":124.0},{"id_colonia":233,"colonia_place_count":1,"colonia_avg_rating":3.6,"colonia_avg_traffic":5.0},{"id_colonia":1370,"colonia_place_count":7,"colonia_avg_rating":4.07,"colonia_avg_traffic":1131.0},{"id_colonia":1115,"colonia_place_count":6,"colonia_avg_rating":3.95,"colonia_avg_traffic":78.0},{"id_colonia":3144,"colonia_place_count":171,"colonia_avg_rating":4.55,"colonia_avg_traffic":107.0},{"id_colonia":2678,"colonia_place_count":2,"colonia_avg_rating":4.3,"colonia_avg_traffic":1253.0},{"id_colonia":884,"colonia_place_count":6,"colonia_avg_rating":4.45,"colonia_avg_traffic":24.0},{"id_colonia":722,"colonia_place_count":93,"colonia_avg_rating":4.36,"colonia_avg_traffic":29.0},{"id_colonia":1286,"colonia_place_count":5,"colonia_avg_rating":4.46,"colonia_avg_traffic":4.0},{"id_colonia":195,"colonia_place_count":1,"colonia_avg_rating":4.0,"colonia_avg_traffic":1.0},{"id_colonia":1374,"colonia_place_count":4,"colonia_avg_rating":4.3,"colonia_avg_traffic":8666.0},{"id_colonia":2924,"colonia_place_count":1,"colonia_avg_rating":4.0,"colonia_avg_traffic":15.0},{"id_colonia":243,"colonia_place_count":4,"colonia_avg_rating":4.68,"colonia_avg_traffic":4.0},{"id_colonia":3685,"colonia_place_count":101,"colonia_avg_rating":4.12,"colonia_avg_traffic":928.0},{"id_colonia":1744,"colonia_place_count":1,"colonia_avg_rating":4.3,"colonia_avg_traffic":3.0},{"id_colonia":3350,"colonia_place_count":7,"colonia_avg_rating":4.09,"colonia_avg_traffic":64.0},{"id_colonia":2994,"colonia_place_count":30,"colonia_avg_rating":4.07,"colonia_avg_traffic":1051.0},{"id_colonia":2036,"colonia_place_count":1,"colonia_avg_rating":3.0,"colonia_avg_traffic":2.0},{"id_colonia":2789,"colonia_place_count":5,"colonia_avg_rating":4.76,"colonia_avg_traffic":4.0},{"id_colonia":2876,"colonia_place_count":6,"colonia_avg_rating":3.28,"colonia_avg_traffic":177.0},{"id_colonia":2027,"colonia_place_count":1,"colonia_avg_rating":4.7,"colonia_avg_traffic":3.0},{"id_colonia":2660,"colonia_place_count":37,"colonia_avg_rating":3.85,"colonia_avg_traffic":999.0},{"id_colonia":230,"colonia_place_count":33,"colonia_avg_rating":4.37,"colonia_avg_traffic":5247.0},{"id_colonia":3621,"colonia_place_count":2,"colonia_avg_rating":3.75,"colonia_avg_traffic":3.0},{"id_colonia":1675,"colonia_place_count":1,"colonia_avg_rating":4.5,"colonia_avg_traffic":8.0},{"id_colonia":3399,"colonia_place_count":2,"colonia_avg_rating":4.2,"colonia_avg_traffic":16.0},{"id_colonia":2236,"colonia_place_count":1,"colonia_avg_rating":5.0,"colonia_avg_traffic":3.0},{"id_colonia":1888,"colonia_place_count":1,"colonia_avg_rating":2.7,"colonia_avg_traffic":16.0},{"id_colonia":1917,"colonia_place_count":1,"colonia_avg_rating":5.0,"colonia_avg_traffic":2.0},{"id_colonia":1356,"colonia_place_count":3,"colonia_avg_rating":4.2,"colonia_avg_traffic":636.0},{"id_colonia":2677,"colonia_place_count":152,"colonia_avg_rating":4.12,"colonia_avg_traffic":239.0},{"id_colonia":1451,"colonia_place_count":5,"colonia_avg_rating":4.42,"colonia_avg_traffic":430.0},{"id_colonia":2816,"colonia_place_count":1,"colonia_avg_rating":4.6,"colonia_avg_traffic":51.0},{"id_colonia":3152,"colonia_place_count":1,"colonia_avg_rating":3.5,"colonia_avg_traffic":2.0},{"id_colonia":1927,"colonia_place_count":2,"colonia_avg_rating":2.7,"colonia_avg_traffic":68.0},{"id_colonia":3772,"colonia_place_count":1,"colonia_avg_rating":4.3,"colonia_avg_traffic":31.0},{"id_colonia":621,"colonia_place_count":1,"colonia_avg_rating":4.1,"colonia_avg_traffic":7.0},{"id_colonia":3623,"colonia_place_count":1,"colonia_avg_rating":4.7,"colonia_avg_traffic":809.0},{"id_colonia":1382,"colonia_place_count":5,"colonia_avg_rating":3.56,"colonia_avg_traffic":6451.0},{"id_colonia":1893,"colonia_place_count":4,"colonia_avg_rating":3.88,"colonia_avg_traffic":397.0},{"id_colonia":1206,"colonia_place_count":1,"colonia_avg_rating":4.5,"colonia_avg_traffic":1262.0},{"id_colonia":1010,"colonia_place_count":9,"colonia_avg_rating":3.99,"colonia_avg_traffic":430.0},{"id_colonia":2177,"colonia_place_count":1,"colonia_avg_rating":3.0,"colonia_avg_traffic":2.0},{"id_colonia":3427,"colonia_place_count":1,"colonia_avg_rating":4.2,"colonia_avg_traffic":5647.0},{"id_colonia":2899,"colonia_place_count":2,"colonia_avg_rating":3.05,"colonia_avg_traffic":68.0},{"id_colonia":2387,"colonia_place_count":2,"colonia_avg_rating":4.35,"colonia_avg_traffic":3.0},{"id_colonia":3336,"colonia_place_count":2,"colonia_avg_rating":4.25,"colonia_avg_traffic":2.0},{"id_colonia":908,"colonia_place_count":9,"colonia_avg_rating":3.67,"colonia_avg_traffic":73.0},{"id_colonia":1690,"colonia_place_count":1,"colonia_avg_rating":4.2,"colonia_avg_traffic":17.0},{"id_colonia":713,"colonia_place_count":31,"colonia_avg_rating":4.18,"colonia_avg_traffic":32.0},{"id_colonia":1205,"colonia_place_count":1,"colonia_avg_rating":4.1,"colonia_avg_traffic":162.0},{"id_colonia":930,"colonia_place_count":2,"colonia_avg_rating":4.05,"colonia_avg_traffic":62.0},{"id_colonia":2402,"colonia_place_count":4,"colonia_avg_rating":3.68,"colonia_avg_traffic":89.0},{"id_colonia":2565,"colonia_place_count":4,"colonia_avg_rating":3.75,"colonia_avg_traffic":2900.0},{"id_colonia":322,"colonia_place_count":21,"colonia_avg_rating":4.31,"colonia_avg_traffic":901.0},{"id_colonia":2757,"colonia_place_count":3,"colonia_avg_rating":4.87,"colonia_avg_traffic":11.0},{"id_colonia":3053,"colonia_place_count":2,"colonia_avg_rating":4.6,"colonia_avg_traffic":16.0},{"id_colonia":2767,"colonia_place_count":13,"colonia_avg_rating":3.98,"colonia_avg_traffic":51.0},{"id_colonia":114,"colonia_place_count":1,"colonia_avg_rating":4.1,"colonia_avg_traffic":217.0},{"id_colonia":3716,"colonia_place_count":200,"colonia_avg_rating":4.07,"colonia_avg_traffic":241.0},{"id_colonia":1106,"colonia_place_count":2,"colonia_avg_rating":4.75,"colonia_avg_traffic":41.0},{"id_colonia":1886,"colonia_place_count":4,"colonia_avg_rating":4.33,"colonia_avg_traffic":55.0},{"id_colonia":1052,"colonia_place_count":3,"colonia_avg_rating":4.77,"colonia_avg_traffic":5686.0},{"id_colonia":754,"colonia_place_count":1,"colonia_avg_rating":3.5,"colonia_avg_traffic":70.0},{"id_colonia":65,"colonia_place_count":3,"colonia_avg_rating":3.0,"colonia_avg_traffic":566.0},{"id_colonia":583,"colonia_place_count":8,"colonia_avg_rating":4.65,"colonia_avg_traffic":67.0},{"id_colonia":2450,"colonia_place_count":1,"colonia_avg_rating":3.8,"colonia_avg_traffic":135.0},{"id_colonia":2349,"colonia_place_count":2,"colonia_avg_rating":3.7,"colonia_avg_traffic":2445.0},{"id_colonia":98,"colonia_place_count":7,"colonia_avg_rating":3.81,"colonia_avg_traffic":500.0},{"id_colonia":3622,"colonia_place_count":21,"colonia_avg_rating":4.1,"colonia_avg_traffic":1748.0},{"id_colonia":3434,"colonia_place_count":1,"colonia_avg_rating":4.1,"colonia_avg_traffic":96.0},{"id_colonia":2336,"colonia_place_count":1,"colonia_avg_rating":4.3,"colonia_avg_traffic":1962.0},{"id_colonia":2278,"colonia_place_count":1,"colonia_avg_rating":4.4,"colonia_avg_traffic":30.0},{"id_colonia":950,"colonia_place_count":1,"colonia_avg_rating":5.0,"colonia_avg_traffic":1.0},{"id_colonia":72,"colonia_place_count":1,"colonia_avg_rating":4.6,"colonia_avg_traffic":3546.0},{"id_colonia":3720,"colonia_place_count":30,"colonia_avg_rating":4.37,"colonia_avg_traffic":6.0},{"id_colonia":2603,"colonia_place_count":2,"colonia_avg_rating":4.95,"colonia_avg_traffic":277.0},{"id_colonia":1260,"colonia_place_count":1,"colonia_avg_rating":4.8,"colonia_avg_traffic":16.0},{"id_colonia":77,"colonia_place_count":1,"colonia_avg_rating":4.5,"colonia_avg_traffic":92.0},{"id_colonia":3121,"colonia_place_count":4,"colonia_avg_rating":4.4,"colonia_avg_traffic":4.0},{"id_colonia":232,"colonia_place_count":27,"colonia_avg_rating":4.17,"colonia_avg_traffic":508.0},{"id_colonia":3158,"colonia_place_count":3,"colonia_avg_rating":4.37,"colonia_avg_traffic":122.0},{"id_colonia":1916,"colonia_place_count":1,"colonia_avg_rating":4.0,"colonia_avg_traffic":7.0},{"id_colonia":1784,"colonia_place_count":7,"colonia_avg_rating":4.47,"colonia_avg_traffic":113.0},{"id_colonia":1766,"colonia_place_count":1,"colonia_avg_rating":4.5,"colonia_avg_traffic":36.0},{"id_colonia":353,"colonia_place_count":38,"colonia_avg_rating":4.12,"colonia_avg_traffic":23.0},{"id_colonia":2132,"colonia_place_count":20,"colonia_avg_rating":4.09,"colonia_avg_traffic":1411.0},{"id_colonia":574,"colonia_place_count":1,"colonia_avg_rating":5.0,"colonia_avg_traffic":1.0},{"id_colonia":1305,"colonia_place_count":1,"colonia_avg_rating":4.3,"colonia_avg_traffic":4.0},{"id_colonia":2679,"colonia_place_count":1,"colonia_avg_rating":4.5,"colonia_avg_traffic":272.0},{"id_colonia":3347,"colonia_place_count":6,"colonia_avg_rating":3.5,"colonia_avg_traffic":9.0},{"id_colonia":333,"colonia_place_count":42,"colonia_avg_rating":3.94,"colonia_avg_traffic":1065.0},{"id_colonia":174,"colonia_place_count":18,"colonia_avg_rating":3.88,"colonia_avg_traffic":96.0},{"id_colonia":891,"colonia_place_count":18,"colonia_avg_rating":4.69,"colonia_avg_traffic":16.0},{"id_colonia":1419,"colonia_place_count":2,"colonia_avg_rating":3.7,"colonia_avg_traffic":192.0},{"id_colonia":1790,"colonia_place_count":1,"colonia_avg_rating":5.0,"colonia_avg_traffic":5.0},{"id_colonia":36,"colonia_place_count":18,"colonia_avg_rating":4.12,"colonia_avg_traffic":164.0},{"id_colonia":1802,"colonia_place_count":131,"colonia_avg_rating":4.59,"colonia_avg_traffic":198.0},{"id_colonia":2133,"colonia_place_count":1,"colonia_avg_rating":4.6,"colonia_avg_traffic":602.0},{"id_colonia":3580,"colonia_place_count":90,"colonia_avg_rating":3.91,"colonia_avg_traffic":475.0},{"id_colonia":1703,"colonia_place_count":56,"colonia_avg_rating":3.92,"colonia_avg_traffic":811.0},{"id_colonia":2918,"colonia_place_count":2,"colonia_avg_rating":5.0,"colonia_avg_traffic":3.0},{"id_colonia":2943,"colonia_place_count":1,"colonia_avg_rating":3.2,"colonia_avg_traffic":83.0},{"id_colonia":1588,"colonia_place_count":1,"colonia_avg_rating":5.0,"colonia_avg_traffic":1.0},{"id_colonia":1783,"colonia_place_count":2,"colonia_avg_rating":3.85,"colonia_avg_traffic":75.0},{"id_colonia":2939,"colonia_place_count":2,"colonia_avg_rating":3.15,"colonia_avg_traffic":9.0},{"id_colonia":979,"colonia_place_count":30,"colonia_avg_rating":4.26,"colonia_avg_traffic":235.0},{"id_colonia":2135,"colonia_place_count":3,"colonia_avg_rating":3.57,"colonia_avg_traffic":111.0},{"id_colonia":881,"colonia_place_count":66,"colonia_avg_rating":4.02,"colonia_avg_traffic":140.0},{"id_colonia":3624,"colonia_place_count":4,"colonia_avg_rating":4.38,"colonia_avg_traffic":25.0},{"id_colonia":1758,"colonia_place_count":1,"colonia_avg_rating":2.8,"colonia_avg_traffic":34.0},{"id_colonia":3596,"colonia_place_count":4,"colonia_avg_rating":3.88,"colonia_avg_traffic":91.0},{"id_colonia":1631,"colonia_place_count":1,"colonia_avg_rating":5.0,"colonia_avg_traffic":7.0},{"id_colonia":2163,"colonia_place_count":1,"colonia_avg_rating":4.0,"colonia_avg_traffic":370.0},{"id_colonia":704,"colonia_place_count":6,"colonia_avg_rating":4.53,"colonia_avg_traffic":17.0},{"id_colonia":1680,"colonia_place_count":4,"colonia_avg_rating":3.45,"colonia_avg_traffic":5.0},{"id_colonia":2563,"colonia_place_count":2,"colonia_avg_rating":3.9,"colonia_avg_traffic":1574.0},{"id_colonia":1909,"colonia_place_count":16,"colonia_avg_rating":4.25,"colonia_avg_traffic":524.0},{"id_colonia":308,"colonia_place_count":1,"colonia_avg_rating":4.7,"colonia_avg_traffic":80.0},{"id_colonia":140,"colonia_place_count":3,"colonia_avg_rating":4.67,"colonia_avg_traffic":191.0},{"id_colonia":3388,"colonia_place_count":4,"colonia_avg_rating":3.85,"colonia_avg_traffic":213.0},{"id_colonia":24,"colonia_place_count":6,"colonia_avg_rating":3.87,"colonia_avg_traffic":127.0},{"id_colonia":1736,"colonia_place_count":1,"colonia_avg_rating":4.8,"colonia_avg_traffic":12.0},{"id_colonia":3443,"colonia_place_count":1,"colonia_avg_rating":5.0,"colonia_avg_traffic":6.0},{"id_colonia":2148,"colonia_place_count":2,"colonia_avg_rating":3.95,"colonia_avg_traffic":142.0},{"id_colonia":3719,"colonia_place_count":7,"colonia_avg_rating":4.41,"colonia_avg_traffic":11.0},{"id_colonia":2949,"colonia_place_count":1,"colonia_avg_rating":4.6,"colonia_avg_traffic":11.0},{"id_colonia":1752,"colonia_place_count":1,"colonia_avg_rating":3.8,"colonia_avg_traffic":155.0},{"id_colonia":2021,"colonia_place_count":1,"colonia_avg_rating":4.0,"colonia_avg_traffic":1.0},{"id_colonia":938,"colonia_place_count":1,"colonia_avg_rating":1.0,"colonia_avg_traffic":1.0},{"id_colonia":1158,"colonia_place_count":1,"colonia_avg_rating":4.7,"colonia_avg_traffic":85.0},{"id_colonia":1642,"colonia_place_count":1,"colonia_avg_rating":4.4,"colonia_avg_traffic":36.0},{"id_colonia":184,"colonia_place_count":1,"colonia_avg_rating":3.7,"colonia_avg_traffic":147.0},{"id_colonia":753,"colonia_place_count":23,"colonia_avg_rating":4.41,"colonia_avg_traffic":14.0},{"id_colonia":1580,"colonia_place_count":10,"colonia_avg_rating":4.45,"colonia_avg_traffic":471.0},{"id_colonia":477,"colonia_place_count":1,"colonia_avg_rating":3.7,"colonia_avg_traffic":3.0},{"id_colonia":3429,"colonia_place_count":1,"colonia_avg_rating":4.9,"colonia_avg_traffic":9.0},{"id_colonia":2606,"colonia_place_count":1,"colonia_avg_rating":4.1,"colonia_avg_traffic":3646.0},{"id_colonia":3478,"colonia_place_count":1,"colonia_avg_rating":4.3,"colonia_avg_traffic":96.0},{"id_colonia":3402,"colonia_place_count":5,"colonia_avg_rating":4.84,"colonia_avg_traffic":132.0},{"id_colonia":1799,"colonia_place_count":179,"colonia_avg_rating":4.34,"colonia_avg_traffic":22.0},{"id_colonia":1683,"colonia_place_count":1,"colonia_avg_rating":3.4,"colonia_avg_traffic":7.0},{"id_colonia":2758,"colonia_place_count":4,"colonia_avg_rating":4.28,"colonia_avg_traffic":5.0},{"id_colonia":2813,"colonia_place_count":1,"colonia_avg_rating":3.5,"colonia_avg_traffic":2.0},{"id_colonia":1854,"colonia_place_count":10,"colonia_avg_rating":4.2,"colonia_avg_traffic":363.0},{"id_colonia":2228,"colonia_place_count":20,"colonia_avg_rating":4.17,"colonia_avg_traffic":14.0},{"id_colonia":2423,"colonia_place_count":1,"colonia_avg_rating":4.4,"colonia_avg_traffic":80.0},{"id_colonia":1348,"colonia_place_count":8,"colonia_avg_rating":4.14,"colonia_avg_traffic":479.0},{"id_colonia":1894,"colonia_place_count":3,"colonia_avg_rating":4.13,"colonia_avg_traffic":241.0},{"id_colonia":2841,"colonia_place_count":30,"colonia_avg_rating":4.02,"colonia_avg_traffic":1820.0},{"id_colonia":475,"colonia_place_count":4,"colonia_avg_rating":4.23,"colonia_avg_traffic":571.0},{"id_colonia":3170,"colonia_place_count":22,"colonia_avg_rating":4.45,"colonia_avg_traffic":18.0},{"id_colonia":888,"colonia_place_count":57,"colonia_avg_rating":4.27,"colonia_avg_traffic":139.0},{"id_colonia":269,"colonia_place_count":1,"colonia_avg_rating":4.1,"colonia_avg_traffic":217.0},{"id_colonia":1594,"colonia_place_count":5,"colonia_avg_rating":4.06,"colonia_avg_traffic":40.0},{"id_colonia":1872,"colonia_place_count":13,"colonia_avg_rating":3.5,"colonia_avg_traffic":307.0},{"id_colonia":257,"colonia_place_count":33,"colonia_avg_rating":4.05,"colonia_avg_traffic":88.0},{"id_colonia":3146,"colonia_place_count":3,"colonia_avg_rating":4.03,"colonia_avg_traffic":81.0},{"id_colonia":1308,"colonia_place_count":1,"colonia_avg_rating":1.3,"colonia_avg_traffic":3.0},{"id_colonia":1649,"colonia_place_count":1,"colonia_avg_rating":5.0,"colonia_avg_traffic":1.0},{"id_colonia":1687,"colonia_place_count":2,"colonia_avg_rating":3.45,"colonia_avg_traffic":1143.0},{"id_colonia":3601,"colonia_place_count":1,"colonia_avg_rating":4.0,"colonia_avg_traffic":157.0},{"id_colonia":2756,"colonia_place_count":1,"colonia_avg_rating":1.0,"colonia_avg_traffic":1.0},{"id_colonia":1119,"colonia_place_count":12,"colonia_avg_rating":3.96,"colonia_avg_traffic":1440.0},{"id_colonia":1789,"colonia_place_count":6,"colonia_avg_rating":4.62,"colonia_avg_traffic":5.0},{"id_colonia":3577,"colonia_place_count":5,"colonia_avg_rating":4.16,"colonia_avg_traffic":122.0},{"id_colonia":3206,"colonia_place_count":4,"colonia_avg_rating":3.78,"colonia_avg_traffic":4.0},{"id_colonia":2991,"colonia_place_count":1,"colonia_avg_rating":5.0,"colonia_avg_traffic":1.0},{"id_colonia":913,"colonia_place_count":19,"colonia_avg_rating":4.55,"colonia_avg_traffic":27.0},{"id_colonia":1468,"colonia_place_count":1,"colonia_avg_rating":3.5,"colonia_avg_traffic":24.0},{"id_colonia":2146,"colonia_place_count":4,"colonia_avg_rating":3.73,"colonia_avg_traffic":20.0},{"id_colonia":3457,"colonia_place_count":1,"colonia_avg_rating":3.3,"colonia_avg_traffic":303.0},{"id_colonia":4,"colonia_place_count":1,"colonia_avg_rating":4.3,"colonia_avg_traffic":604.0},{"id_colonia":2765,"colonia_place_count":4,"colonia_avg_rating":4.05,"colonia_avg_traffic":217.0},{"id_colonia":3318,"colonia_place_count":1,"colonia_avg_rating":3.6,"colonia_avg_traffic":72.0},{"id_colonia":3154,"colonia_place_count":419,"colonia_avg_rating":4.11,"colonia_avg_traffic":133.0},{"id_colonia":2853,"colonia_place_count":1,"colonia_avg_rating":5.0,"colonia_avg_traffic":1.0},{"id_colonia":1890,"colonia_place_count":3,"colonia_avg_rating":3.83,"colonia_avg_traffic":67.0},{"id_colonia":1787,"colonia_place_count":1,"colonia_avg_rating":4.4,"colonia_avg_traffic":5.0},{"id_colonia":1039,"colonia_place_count":1,"colonia_avg_rating":4.3,"colonia_avg_traffic":3471.0},{"id_colonia":631,"colonia_place_count":4,"colonia_avg_rating":4.33,"colonia_avg_traffic":3843.0},{"id_colonia":1778,"colonia_place_count":1,"colonia_avg_rating":3.0,"colonia_avg_traffic":1.0},{"id_colonia":1314,"colonia_place_count":1,"colonia_avg_rating":5.0,"colonia_avg_traffic":1.0},{"id_colonia":6,"colonia_place_count":2,"colonia_avg_rating":4.15,"colonia_avg_traffic":858.0},{"id_colonia":446,"colonia_place_count":1,"colonia_avg_rating":4.4,"colonia_avg_traffic":78.0},{"id_colonia":749,"colonia_place_count":1,"colonia_avg_rating":4.2,"colonia_avg_traffic":46.0},{"id_colonia":3366,"colonia_place_count":3,"colonia_avg_rating":4.2,"colonia_avg_traffic":5.0},{"id_colonia":86,"colonia_place_count":1,"colonia_avg_rating":4.5,"colonia_avg_traffic":21013.0},{"id_colonia":1148,"colonia_place_count":2,"colonia_avg_rating":4.25,"colonia_avg_traffic":1467.0},{"id_colonia":3321,"colonia_place_count":2,"colonia_avg_rating":4.65,"colonia_avg_traffic":1238.0},{"id_colonia":3509,"colonia_place_count":2,"colonia_avg_rating":4.75,"colonia_avg_traffic":80.0},{"id_colonia":3667,"colonia_place_count":3,"colonia_avg_rating":3.93,"colonia_avg_traffic":7.0},{"id_colonia":2351,"colonia_place_count":1,"colonia_avg_rating":4.9,"colonia_avg_traffic":30.0},{"id_colonia":661,"colonia_place_count":205,"colonia_avg_rating":4.29,"colonia_avg_traffic":42.0},{"id_colonia":3801,"colonia_place_count":1,"colonia_avg_rating":4.7,"colonia_avg_traffic":15.0},{"id_colonia":523,"colonia_place_count":1,"colonia_avg_rating":3.7,"colonia_avg_traffic":328.0},{"id_colonia":3501,"colonia_place_count":5,"colonia_avg_rating":3.86,"colonia_avg_traffic":11.0},{"id_colonia":1919,"colonia_place_count":120,"colonia_avg_rating":3.99,"colonia_avg_traffic":2779.0},{"id_colonia":1803,"colonia_place_count":35,"colonia_avg_rating":4.3,"colonia_avg_traffic":90.0},{"id_colonia":1572,"colonia_place_count":2,"colonia_avg_rating":3.85,"colonia_avg_traffic":7.0},{"id_colonia":368,"colonia_place_count":25,"colonia_avg_rating":4.0,"colonia_avg_traffic":400.0},{"id_colonia":3164,"colonia_place_count":1,"colonia_avg_rating":3.3,"colonia_avg_traffic":18.0},{"id_colonia":2917,"colonia_place_count":35,"colonia_avg_rating":4.34,"colonia_avg_traffic":13.0},{"id_colonia":1850,"colonia_place_count":20,"colonia_avg_rating":4.05,"colonia_avg_traffic":254.0},{"id_colonia":595,"colonia_place_count":27,"colonia_avg_rating":4.11,"colonia_avg_traffic":325.0},{"id_colonia":2167,"colonia_place_count":2,"colonia_avg_rating":2.85,"colonia_avg_traffic":4.0},{"id_colonia":142,"colonia_place_count":3,"colonia_avg_rating":4.53,"colonia_avg_traffic":68.0},{"id_colonia":1054,"colonia_place_count":3,"colonia_avg_rating":3.87,"colonia_avg_traffic":268.0},{"id_colonia":792,"colonia_place_count":1,"colonia_avg_rating":2.7,"colonia_avg_traffic":310.0},{"id_colonia":2189,"colonia_place_count":1,"colonia_avg_rating":2.8,"colonia_avg_traffic":5.0},{"id_colonia":896,"colonia_place_count":25,"colonia_avg_rating":4.45,"colonia_avg_traffic":37.0},{"id_colonia":1381,"colonia_place_count":6,"colonia_avg_rating":3.98,"colonia_avg_traffic":1718.0},{"id_colonia":597,"colonia_place_count":3,"colonia_avg_rating":4.67,"colonia_avg_traffic":32.0},{"id_colonia":3537,"colonia_place_count":4,"colonia_avg_rating":4.38,"colonia_avg_traffic":18.0},{"id_colonia":3678,"colonia_place_count":3,"colonia_avg_rating":4.33,"colonia_avg_traffic":8.0},{"id_colonia":1902,"colonia_place_count":1,"colonia_avg_rating":5.0,"colonia_avg_traffic":1.0},{"id_colonia":177,"colonia_place_count":1,"colonia_avg_rating":4.2,"colonia_avg_traffic":1750.0},{"id_colonia":886,"colonia_place_count":1,"colonia_avg_rating":4.0,"colonia_avg_traffic":23.0},{"id_colonia":727,"colonia_place_count":2,"colonia_avg_rating":4.5,"colonia_avg_traffic":52.0},{"id_colonia":3490,"colonia_place_count":349,"colonia_avg_rating":4.32,"colonia_avg_traffic":34.0},{"id_colonia":3248,"colonia_place_count":1,"colonia_avg_rating":3.8,"colonia_avg_traffic":46.0},{"id_colonia":3390,"colonia_place_count":10,"colonia_avg_rating":4.59,"colonia_avg_traffic":4.0},{"id_colonia":2877,"colonia_place_count":1,"colonia_avg_rating":3.9,"colonia_avg_traffic":1521.0},{"id_colonia":1405,"colonia_place_count":3,"colonia_avg_rating":4.37,"colonia_avg_traffic":409.0},{"id_colonia":2856,"colonia_place_count":19,"colonia_avg_rating":4.31,"colonia_avg_traffic":1509.0},{"id_colonia":1231,"colonia_place_count":3,"colonia_avg_rating":3.93,"colonia_avg_traffic":9492.0},{"id_colonia":2658,"colonia_place_count":5,"colonia_avg_rating":3.36,"colonia_avg_traffic":353.0},{"id_colonia":3594,"colonia_place_count":1,"colonia_avg_rating":4.9,"colonia_avg_traffic":14.0},{"id_colonia":1706,"colonia_place_count":2,"colonia_avg_rating":4.25,"colonia_avg_traffic":94.0},{"id_colonia":718,"colonia_place_count":4,"colonia_avg_rating":4.28,"colonia_avg_traffic":107.0},{"id_colonia":623,"colonia_place_count":7,"colonia_avg_rating":4.46,"colonia_avg_traffic":70.0},{"id_colonia":1388,"colonia_place_count":1,"colonia_avg_rating":2.4,"colonia_avg_traffic":126.0},{"id_colonia":3668,"colonia_place_count":5,"colonia_avg_rating":4.06,"colonia_avg_traffic":167.0},{"id_colonia":2763,"colonia_place_count":2,"colonia_avg_rating":4.5,"colonia_avg_traffic":3.0},{"id_colonia":2915,"colonia_place_count":1,"colonia_avg_rating":1.0,"colonia_avg_traffic":1.0},{"id_colonia":2338,"colonia_place_count":1,"colonia_avg_rating":4.3,"colonia_avg_traffic":105.0},{"id_colonia":1198,"colonia_place_count":8,"colonia_avg_rating":4.05,"colonia_avg_traffic":1038.0},{"id_colonia":3579,"colonia_place_count":2,"colonia_avg_rating":4.75,"colonia_avg_traffic":2.0},{"id_colonia":3395,"colonia_place_count":1,"colonia_avg_rating":3.7,"colonia_avg_traffic":1535.0},{"id_colonia":170,"colonia_place_count":3,"colonia_avg_rating":4.67,"colonia_avg_traffic":17.0},{"id_colonia":712,"colonia_place_count":3,"colonia_avg_rating":3.43,"colonia_avg_traffic":6.0},{"id_colonia":192,"colonia_place_count":1,"colonia_avg_rating":4.3,"colonia_avg_traffic":30.0},{"id_colonia":1696,"colonia_place_count":1,"colonia_avg_rating":4.1,"colonia_avg_traffic":98.0},{"id_colonia":1740,"colonia_place_count":3,"colonia_avg_rating":4.07,"colonia_avg_traffic":62.0},{"id_colonia":69,"colonia_place_count":1,"colonia_avg_rating":4.7,"colonia_avg_traffic":563.0},{"id_colonia":1824,"colonia_place_count":1,"colonia_avg_rating":1.0,"colonia_avg_traffic":2.0},{"id_colonia":2369,"colonia_place_count":1,"colonia_avg_rating":4.2,"colonia_avg_traffic":5.0},{"id_colonia":679,"colonia_place_count":5,"colonia_avg_rating":3.28,"colonia_avg_traffic":28.0},{"id_colonia":1912,"colonia_place_count":1,"colonia_avg_rating":2.6,"colonia_avg_traffic":43.0},{"id_colonia":976,"colonia_place_count":26,"colonia_avg_rating":4.14,"colonia_avg_traffic":1783.0},{"id_colonia":3142,"colonia_place_count":8,"colonia_avg_rating":4.46,"colonia_avg_traffic":47.0},{"id_colonia":1835,"colonia_place_count":3,"colonia_avg_rating":3.67,"colonia_avg_traffic":11.0},{"id_colonia":1376,"colonia_place_count":10,"colonia_avg_rating":4.2,"colonia_avg_traffic":4966.0},{"id_colonia":1365,"colonia_place_count":9,"colonia_avg_rating":4.17,"colonia_avg_traffic":1954.0},{"id_colonia":1338,"colonia_place_count":6,"colonia_avg_rating":4.03,"colonia_avg_traffic":554.0},{"id_colonia":1723,"colonia_place_count":1,"colonia_avg_rating":4.7,"colonia_avg_traffic":3.0},{"id_colonia":1330,"colonia_place_count":1,"colonia_avg_rating":5.0,"colonia_avg_traffic":1.0},{"id_colonia":821,"colonia_place_count":1,"colonia_avg_rating":4.6,"colonia_avg_traffic":10.0},{"id_colonia":401,"colonia_place_count":2,"colonia_avg_rating":3.5,"colonia_avg_traffic":2780.0},{"id_colonia":1701,"colonia_place_count":4,"colonia_avg_rating":4.38,"colonia_avg_traffic":203.0},{"id_colonia":3711,"colonia_place_count":27,"colonia_avg_rating":4.14,"colonia_avg_traffic":1573.0},{"id_colonia":2613,"colonia_place_count":1,"colonia_avg_rating":4.4,"colonia_avg_traffic":1009.0},{"id_colonia":3698,"colonia_place_count":2,"colonia_avg_rating":4.6,"colonia_avg_traffic":38.0},{"id_colonia":1948,"colonia_place_count":36,"colonia_avg_rating":3.79,"colonia_avg_traffic":302.0},{"id_colonia":1743,"colonia_place_count":2,"colonia_avg_rating":3.35,"colonia_avg_traffic":11.0},{"id_colonia":897,"colonia_place_count":10,"colonia_avg_rating":4.14,"colonia_avg_traffic":24.0},{"id_colonia":565,"colonia_place_count":1,"colonia_avg_rating":4.0,"colonia_avg_traffic":1.0},{"id_colonia":1947,"colonia_place_count":6,"colonia_avg_rating":4.32,"colonia_avg_traffic":6.0},{"id_colonia":3640,"colonia_place_count":28,"colonia_avg_rating":4.33,"colonia_avg_traffic":636.0},{"id_colonia":3209,"colonia_place_count":2,"colonia_avg_rating":4.0,"colonia_avg_traffic":58.0},{"id_colonia":2662,"colonia_place_count":2,"colonia_avg_rating":4.0,"colonia_avg_traffic":418.0},{"id_colonia":2798,"colonia_place_count":1,"colonia_avg_rating":4.0,"colonia_avg_traffic":41.0},{"id_colonia":21,"colonia_place_count":106,"colonia_avg_rating":4.47,"colonia_avg_traffic":1335.0},{"id_colonia":622,"colonia_place_count":10,"colonia_avg_rating":4.69,"colonia_avg_traffic":16.0},{"id_colonia":927,"colonia_place_count":2,"colonia_avg_rating":4.25,"colonia_avg_traffic":224.0},{"id_colonia":3385,"colonia_place_count":1,"colonia_avg_rating":4.2,"colonia_avg_traffic":1616.0},{"id_colonia":1832,"colonia_place_count":33,"colonia_avg_rating":4.26,"colonia_avg_traffic":101.0},{"id_colonia":1726,"colonia_place_count":1,"colonia_avg_rating":4.5,"colonia_avg_traffic":1333.0},{"id_colonia":635,"colonia_place_count":1,"colonia_avg_rating":5.0,"colonia_avg_traffic":1.0},{"id_colonia":2162,"colonia_place_count":2,"colonia_avg_rating":3.95,"colonia_avg_traffic":3676.0},{"id_colonia":56,"colonia_place_count":28,"colonia_avg_rating":4.03,"colonia_avg_traffic":383.0},{"id_colonia":3155,"colonia_place_count":4,"colonia_avg_rating":4.55,"colonia_avg_traffic":1749.0},{"id_colonia":67,"colonia_place_count":3,"colonia_avg_rating":3.4,"colonia_avg_traffic":69.0},{"id_colonia":325,"colonia_place_count":10,"colonia_avg_rating":4.34,"colonia_avg_traffic":218.0},{"id_colonia":1377,"colonia_place_count":25,"colonia_avg_rating":4.12,"colonia_avg_traffic":881.0},{"id_colonia":1127,"colonia_place_count":8,"colonia_avg_rating":4.16,"colonia_avg_traffic":893.0},{"id_colonia":2348,"colonia_place_count":1,"colonia_avg_rating":5.0,"colonia_avg_traffic":4.0},{"id_colonia":1794,"colonia_place_count":137,"colonia_avg_rating":4.46,"colonia_avg_traffic":51.0},{"id_colonia":598,"colonia_place_count":9,"colonia_avg_rating":4.08,"colonia_avg_traffic":6.0},{"id_colonia":1930,"colonia_place_count":5,"colonia_avg_rating":3.22,"colonia_avg_traffic":102.0},{"id_colonia":1051,"colonia_place_count":1,"colonia_avg_rating":4.7,"colonia_avg_traffic":5765.0},{"id_colonia":2566,"colonia_place_count":12,"colonia_avg_rating":4.29,"colonia_avg_traffic":1216.0},{"id_colonia":2511,"colonia_place_count":8,"colonia_avg_rating":4.01,"colonia_avg_traffic":1531.0},{"id_colonia":167,"colonia_place_count":1,"colonia_avg_rating":5.0,"colonia_avg_traffic":2.0},{"id_colonia":3747,"colonia_place_count":1,"colonia_avg_rating":4.2,"colonia_avg_traffic":68.0},{"id_colonia":2499,"colonia_place_count":8,"colonia_avg_rating":4.33,"colonia_avg_traffic":65.0},{"id_colonia":2261,"colonia_place_count":1,"colonia_avg_rating":4.3,"colonia_avg_traffic":298.0},{"id_colonia":277,"colonia_place_count":12,"colonia_avg_rating":4.11,"colonia_avg_traffic":43.0},{"id_colonia":3043,"colonia_place_count":3,"colonia_avg_rating":4.07,"colonia_avg_traffic":120.0},{"id_colonia":1859,"colonia_place_count":8,"colonia_avg_rating":4.39,"colonia_avg_traffic":198.0},{"id_colonia":2794,"colonia_place_count":3,"colonia_avg_rating":3.87,"colonia_avg_traffic":8.0},{"id_colonia":2729,"colonia_place_count":1,"colonia_avg_rating":2.3,"colonia_avg_traffic":3.0},{"id_colonia":3238,"colonia_place_count":6,"colonia_avg_rating":3.6,"colonia_avg_traffic":30.0},{"id_colonia":3414,"colonia_place_count":3,"colonia_avg_rating":4.57,"colonia_avg_traffic":69.0},{"id_colonia":1271,"colonia_place_count":3,"colonia_avg_rating":3.97,"colonia_avg_traffic":239.0},{"id_colonia":1035,"colonia_place_count":1,"colonia_avg_rating":4.8,"colonia_avg_traffic":21.0},{"id_colonia":46,"colonia_place_count":2,"colonia_avg_rating":4.45,"colonia_avg_traffic":26874.0},{"id_colonia":2091,"colonia_place_count":3,"colonia_avg_rating":3.97,"colonia_avg_traffic":65.0},{"id_colonia":3361,"colonia_place_count":1,"colonia_avg_rating":3.8,"colonia_avg_traffic":16.0},{"id_colonia":1801,"colonia_place_count":2,"colonia_avg_rating":4.75,"colonia_avg_traffic":57.0},{"id_colonia":3662,"colonia_place_count":6,"colonia_avg_rating":3.75,"colonia_avg_traffic":2.0},{"id_colonia":2820,"colonia_place_count":3,"colonia_avg_rating":3.93,"colonia_avg_traffic":49.0},{"id_colonia":2184,"colonia_place_count":1,"colonia_avg_rating":3.4,"colonia_avg_traffic":9.0},{"id_colonia":136,"colonia_place_count":4,"colonia_avg_rating":4.45,"colonia_avg_traffic":6.0},{"id_colonia":1240,"colonia_place_count":35,"colonia_avg_rating":4.1,"colonia_avg_traffic":381.0},{"id_colonia":1881,"colonia_place_count":3,"colonia_avg_rating":3.13,"colonia_avg_traffic":28.0},{"id_colonia":1946,"colonia_place_count":6,"colonia_avg_rating":4.28,"colonia_avg_traffic":1744.0},{"id_colonia":3087,"colonia_place_count":1,"colonia_avg_rating":4.5,"colonia_avg_traffic":461.0},{"id_colonia":1868,"colonia_place_count":11,"colonia_avg_rating":4.35,"colonia_avg_traffic":471.0},{"id_colonia":1734,"colonia_place_count":1,"colonia_avg_rating":4.2,"colonia_avg_traffic":259.0},{"id_colonia":1584,"colonia_place_count":3,"colonia_avg_rating":3.87,"colonia_avg_traffic":55.0},{"id_colonia":1040,"colonia_place_count":24,"colonia_avg_rating":3.84,"colonia_avg_traffic":45.0},{"id_colonia":2805,"colonia_place_count":26,"colonia_avg_rating":4.22,"colonia_avg_traffic":214.0},{"id_colonia":2639,"colonia_place_count":1,"colonia_avg_rating":3.9,"colonia_avg_traffic":30.0},{"id_colonia":3459,"colonia_place_count":1,"colonia_avg_rating":2.5,"colonia_avg_traffic":4.0},{"id_colonia":2801,"colonia_place_count":18,"colonia_avg_rating":4.49,"colonia_avg_traffic":11.0},{"id_colonia":3337,"colonia_place_count":3,"colonia_avg_rating":4.57,"colonia_avg_traffic":130.0},{"id_colonia":3145,"colonia_place_count":1,"colonia_avg_rating":5.0,"colonia_avg_traffic":1.0},{"id_colonia":885,"colonia_place_count":12,"colonia_avg_rating":4.23,"colonia_avg_traffic":54.0},{"id_colonia":3108,"colonia_place_count":32,"colonia_avg_rating":3.97,"colonia_avg_traffic":227.0},{"id_colonia":215,"colonia_place_count":2,"colonia_avg_rating":4.5,"colonia_avg_traffic":14.0},{"id_colonia":2554,"colonia_place_count":1,"colonia_avg_rating":4.5,"colonia_avg_traffic":28.0},{"id_colonia":1275,"colonia_place_count":1,"colonia_avg_rating":4.5,"colonia_avg_traffic":4.0},{"id_colonia":2744,"colonia_place_count":347,"colonia_avg_rating":4.37,"colonia_avg_traffic":252.0},{"id_colonia":130,"colonia_place_count":1,"colonia_avg_rating":5.0,"colonia_avg_traffic":4.0},{"id_colonia":1157,"colonia_place_count":2,"colonia_avg_rating":4.85,"colonia_avg_traffic":8.0},{"id_colonia":3648,"colonia_place_count":1,"colonia_avg_rating":4.7,"colonia_avg_traffic":68.0},{"id_colonia":1155,"colonia_place_count":2,"colonia_avg_rating":3.65,"colonia_avg_traffic":73.0},{"id_colonia":617,"colonia_place_count":1,"colonia_avg_rating":3.9,"colonia_avg_traffic":18.0},{"id_colonia":3581,"colonia_place_count":6,"colonia_avg_rating":3.77,"colonia_avg_traffic":50.0},{"id_colonia":3141,"colonia_place_count":2,"colonia_avg_rating":4.25,"colonia_avg_traffic":16.0},{"id_colonia":765,"colonia_place_count":1,"colonia_avg_rating":4.8,"colonia_avg_traffic":80.0},{"id_colonia":887,"colonia_place_count":20,"colonia_avg_rating":4.62,"colonia_avg_traffic":88.0},{"id_colonia":3265,"colonia_place_count":2,"colonia_avg_rating":3.75,"colonia_avg_traffic":24.0},{"id_colonia":1669,"colonia_place_count":1,"colonia_avg_rating":5.0,"colonia_avg_traffic":1.0},{"id_colonia":3797,"colonia_place_count":2,"colonia_avg_rating":4.45,"colonia_avg_traffic":2680.0},{"id_colonia":2022,"colonia_place_count":1,"colonia_avg_rating":4.3,"colonia_avg_traffic":141.0},{"id_colonia":819,"colonia_place_count":5,"colonia_avg_rating":3.74,"colonia_avg_traffic":18.0},{"id_colonia":1983,"colonia_place_count":1,"colonia_avg_rating":5.0,"colonia_avg_traffic":2.0},{"id_colonia":1274,"colonia_place_count":1,"colonia_avg_rating":4.1,"colonia_avg_traffic":32.0},{"id_colonia":1891,"colonia_place_count":2,"colonia_avg_rating":3.75,"colonia_avg_traffic":43.0},{"id_colonia":1797,"colonia_place_count":7,"colonia_avg_rating":4.24,"colonia_avg_traffic":3.0},{"id_colonia":364,"colonia_place_count":1,"colonia_avg_rating":3.0,"colonia_avg_traffic":2.0},{"id_colonia":2822,"colonia_place_count":1,"colonia_avg_rating":5.0,"colonia_avg_traffic":2.0},{"id_colonia":1123,"colonia_place_count":2,"colonia_avg_rating":4.5,"colonia_avg_traffic":5.0},{"id_colonia":345,"colonia_place_count":15,"colonia_avg_rating":3.91,"colonia_avg_traffic":294.0},{"id_colonia":1517,"colonia_place_count":1,"colonia_avg_rating":3.9,"colonia_avg_traffic":1062.0},{"id_colonia":1702,"colonia_place_count":7,"colonia_avg_rating":4.13,"colonia_avg_traffic":163.0},{"id_colonia":1707,"colonia_place_count":79,"colonia_avg_rating":4.26,"colonia_avg_traffic":38.0},{"id_colonia":2761,"colonia_place_count":9,"colonia_avg_rating":4.33,"colonia_avg_traffic":52.0},{"id_colonia":3546,"colonia_place_count":1,"colonia_avg_rating":3.0,"colonia_avg_traffic":5.0},{"id_colonia":707,"colonia_place_count":4,"colonia_avg_rating":4.68,"colonia_avg_traffic":4.0},{"id_colonia":1751,"colonia_place_count":1,"colonia_avg_rating":5.0,"colonia_avg_traffic":2.0},{"id_colonia":2802,"colonia_place_count":1,"colonia_avg_rating":4.0,"colonia_avg_traffic":52.0},{"id_colonia":3197,"colonia_place_count":1,"colonia_avg_rating":4.2,"colonia_avg_traffic":5.0},{"id_colonia":3143,"colonia_place_count":2,"colonia_avg_rating":4.5,"colonia_avg_traffic":52.0},{"id_colonia":2769,"colonia_place_count":2,"colonia_avg_rating":4.65,"colonia_avg_traffic":4.0},{"id_colonia":1651,"colonia_place_count":1,"colonia_avg_rating":4.3,"colonia_avg_traffic":45.0},{"id_colonia":3188,"colonia_place_count":1,"colonia_avg_rating":4.3,"colonia_avg_traffic":2996.0},{"id_colonia":561,"colonia_place_count":1,"colonia_avg_rating":4.2,"colonia_avg_traffic":6669.0},{"id_colonia":3729,"colonia_place_count":1,"colonia_avg_rating":5.0,"colonia_avg_traffic":1.0},{"id_colonia":1865,"colonia_place_count":1,"colonia_avg_rating":4.5,"colonia_avg_traffic":122.0},{"id_colonia":1069,"colonia_place_count":3,"colonia_avg_rating":4.8,"colonia_avg_traffic":9.0},{"id_colonia":1129,"colonia_place_count":13,"colonia_avg_rating":3.89,"colonia_avg_traffic":342.0},{"id_colonia":767,"colonia_place_count":1,"colonia_avg_rating":2.4,"colonia_avg_traffic":158.0},{"id_colonia":2386,"colonia_place_count":1,"colonia_avg_rating":4.1,"colonia_avg_traffic":44.0},{"id_colonia":1367,"colonia_place_count":3,"colonia_avg_rating":3.07,"colonia_avg_traffic":78.0},{"id_colonia":61,"colonia_place_count":29,"colonia_avg_rating":4.24,"colonia_avg_traffic":398.0},{"id_colonia":1088,"colonia_place_count":1,"colonia_avg_rating":2.2,"colonia_avg_traffic":96.0},{"id_colonia":691,"colonia_place_count":8,"colonia_avg_rating":4.04,"colonia_avg_traffic":398.0},{"id_colonia":1124,"colonia_place_count":7,"colonia_avg_rating":4.34,"colonia_avg_traffic":712.0},{"id_colonia":1717,"colonia_place_count":2,"colonia_avg_rating":4.05,"colonia_avg_traffic":5397.0},{"id_colonia":1738,"colonia_place_count":14,"colonia_avg_rating":4.08,"colonia_avg_traffic":654.0},{"id_colonia":1243,"colonia_place_count":4,"colonia_avg_rating":4.15,"colonia_avg_traffic":1434.0},{"id_colonia":721,"colonia_place_count":7,"colonia_avg_rating":4.39,"colonia_avg_traffic":29.0},{"id_colonia":251,"colonia_place_count":1,"colonia_avg_rating":4.5,"colonia_avg_traffic":4.0},{"id_colonia":1100,"colonia_place_count":3,"colonia_avg_rating":4.8,"colonia_avg_traffic":31.0},{"id_colonia":705,"colonia_place_count":20,"colonia_avg_rating":4.72,"colonia_avg_traffic":14.0},{"id_colonia":104,"colonia_place_count":2,"colonia_avg_rating":3.9,"colonia_avg_traffic":161.0},{"id_colonia":2842,"colonia_place_count":260,"colonia_avg_rating":4.08,"colonia_avg_traffic":2746.0},{"id_colonia":2325,"colonia_place_count":1,"colonia_avg_rating":4.5,"colonia_avg_traffic":6.0},{"id_colonia":1270,"colonia_place_count":1,"colonia_avg_rating":4.3,"colonia_avg_traffic":423.0},{"id_colonia":2379,"colonia_place_count":3,"colonia_avg_rating":3.67,"colonia_avg_traffic":11.0},{"id_colonia":171,"colonia_place_count":1,"colonia_avg_rating":4.4,"colonia_avg_traffic":53.0},{"id_colonia":960,"colonia_place_count":9,"colonia_avg_rating":4.0,"colonia_avg_traffic":58.0},{"id_colonia":1729,"colonia_place_count":8,"colonia_avg_rating":3.93,"colonia_avg_traffic":222.0},{"id_colonia":427,"colonia_place_count":1,"colonia_avg_rating":5.0,"colonia_avg_traffic":2.0},{"id_colonia":604,"colonia_place_count":9,"colonia_avg_rating":4.13,"colonia_avg_traffic":123.0},{"id_colonia":786,"colonia_place_count":3,"colonia_avg_rating":4.07,"colonia_avg_traffic":18.0},{"id_colonia":3695,"colonia_place_count":1,"colonia_avg_rating":4.3,"colonia_avg_traffic":33.0},{"id_colonia":1945,"colonia_place_count":2,"colonia_avg_rating":3.6,"colonia_avg_traffic":1671.0},{"id_colonia":2424,"colonia_place_count":5,"colonia_avg_rating":4.32,"colonia_avg_traffic":8.0},{"id_colonia":402,"colonia_place_count":4,"colonia_avg_rating":3.58,"colonia_avg_traffic":404.0},{"id_colonia":804,"colonia_place_count":44,"colonia_avg_rating":4.59,"colonia_avg_traffic":420.0},{"id_colonia":3410,"colonia_place_count":13,"colonia_avg_rating":4.17,"colonia_avg_traffic":46.0},{"id_colonia":1934,"colonia_place_count":4,"colonia_avg_rating":4.3,"colonia_avg_traffic":98.0},{"id_colonia":3139,"colonia_place_count":1,"colonia_avg_rating":4.2,"colonia_avg_traffic":24.0},{"id_colonia":889,"colonia_place_count":2,"colonia_avg_rating":4.1,"colonia_avg_traffic":16.0},{"id_colonia":1542,"colonia_place_count":1,"colonia_avg_rating":3.8,"colonia_avg_traffic":4.0},{"id_colonia":1611,"colonia_place_count":1,"colonia_avg_rating":4.4,"colonia_avg_traffic":1426.0},{"id_colonia":1724,"colonia_place_count":2,"colonia_avg_rating":4.05,"colonia_avg_traffic":32.0},{"id_colonia":3724,"colonia_place_count":1,"colonia_avg_rating":4.0,"colonia_avg_traffic":6.0},{"id_colonia":776,"colonia_place_count":1,"colonia_avg_rating":3.9,"colonia_avg_traffic":27.0},{"id_colonia":2026,"colonia_place_count":1,"colonia_avg_rating":3.8,"colonia_avg_traffic":88.0},{"id_colonia":1636,"colonia_place_count":1,"colonia_avg_rating":3.1,"colonia_avg_traffic":11.0},{"id_colonia":253,"colonia_place_count":2,"colonia_avg_rating":4.35,"colonia_avg_traffic":187.0},{"id_colonia":692,"colonia_place_count":1,"colonia_avg_rating":5.0,"colonia_avg_traffic":1.0},{"id_colonia":14,"colonia_place_count":2,"colonia_avg_rating":3.6,"colonia_avg_traffic":18208.0},{"id_colonia":1369,"colonia_place_count":13,"colonia_avg_rating":4.37,"colonia_avg_traffic":231.0},{"id_colonia":1121,"colonia_place_count":1,"colonia_avg_rating":4.5,"colonia_avg_traffic":1473.0},{"id_colonia":1882,"colonia_place_count":2,"colonia_avg_rating":4.65,"colonia_avg_traffic":7.0},{"id_colonia":3075,"colonia_place_count":1,"colonia_avg_rating":5.0,"colonia_avg_traffic":1.0},{"id_colonia":3334,"colonia_place_count":1,"colonia_avg_rating":3.6,"colonia_avg_traffic":724.0},{"id_colonia":1566,"colonia_place_count":13,"colonia_avg_rating":4.4,"colonia_avg_traffic":15.0},{"id_colonia":724,"colonia_place_count":1,"colonia_avg_rating":5.0,"colonia_avg_traffic":19.0},{"id_colonia":1785,"colonia_place_count":1,"colonia_avg_rating":3.7,"colonia_avg_traffic":3.0},{"id_colonia":1323,"colonia_place_count":6,"colonia_avg_rating":4.2,"colonia_avg_traffic":130.0},{"id_colonia":1237,"colonia_place_count":23,"colonia_avg_rating":3.91,"colonia_avg_traffic":20.0},{"id_colonia":339,"colonia_place_count":3,"colonia_avg_rating":4.2,"colonia_avg_traffic":10.0},{"id_colonia":2019,"colonia_place_count":3,"colonia_avg_rating":3.93,"colonia_avg_traffic":541.0},{"id_colonia":1596,"colonia_place_count":1,"colonia_avg_rating":3.3,"colonia_avg_traffic":4.0},{"id_colonia":1818,"colonia_place_count":188,"colonia_avg_rating":4.35,"colonia_avg_traffic":153.0},{"id_colonia":603,"colonia_place_count":13,"colonia_avg_rating":4.52,"colonia_avg_traffic":23.0},{"id_colonia":808,"colonia_place_count":5,"colonia_avg_rating":4.28,"colonia_avg_traffic":989.0},{"id_colonia":301,"colonia_place_count":1,"colonia_avg_rating":4.2,"colonia_avg_traffic":42.0},{"id_colonia":7,"colonia_place_count":22,"colonia_avg_rating":4.39,"colonia_avg_traffic":1409.0},{"id_colonia":1011,"colonia_place_count":2,"colonia_avg_rating":4.75,"colonia_avg_traffic":133.0},{"id_colonia":3704,"colonia_place_count":194,"colonia_avg_rating":4.12,"colonia_avg_traffic":639.0},{"id_colonia":3104,"colonia_place_count":28,"colonia_avg_rating":4.24,"colonia_avg_traffic":28.0},{"id_colonia":1061,"colonia_place_count":18,"colonia_avg_rating":4.21,"colonia_avg_traffic":207.0},{"id_colonia":1341,"colonia_place_count":18,"colonia_avg_rating":4.12,"colonia_avg_traffic":24.0},{"id_colonia":319,"colonia_place_count":17,"colonia_avg_rating":4.38,"colonia_avg_traffic":899.0},{"id_colonia":1,"colonia_place_count":21,"colonia_avg_rating":4.28,"colonia_avg_traffic":1148.0},{"id_colonia":76,"colonia_place_count":3,"colonia_avg_rating":4.93,"colonia_avg_traffic":23.0},{"id_colonia":517,"colonia_place_count":1,"colonia_avg_rating":4.4,"colonia_avg_traffic":18.0},{"id_colonia":3485,"colonia_place_count":76,"colonia_avg_rating":4.56,"colonia_avg_traffic":16.0},{"id_colonia":1082,"colonia_place_count":2,"colonia_avg_rating":4.95,"colonia_avg_traffic":99.0},{"id_colonia":1392,"colonia_place_count":1,"colonia_avg_rating":4.0,"colonia_avg_traffic":43.0},{"id_colonia":2779,"colonia_place_count":1,"colonia_avg_rating":2.0,"colonia_avg_traffic":3.0},{"id_colonia":3052,"colonia_place_count":13,"colonia_avg_rating":4.2,"colonia_avg_traffic":106.0},{"id_colonia":1002,"colonia_place_count":7,"colonia_avg_rating":4.13,"colonia_avg_traffic":452.0},{"id_colonia":3297,"colonia_place_count":1,"colonia_avg_rating":4.6,"colonia_avg_traffic":38.0},{"id_colonia":3721,"colonia_place_count":2,"colonia_avg_rating":4.55,"colonia_avg_traffic":11.0},{"id_colonia":1817,"colonia_place_count":1,"colonia_avg_rating":5.0,"colonia_avg_traffic":1.0},{"id_colonia":2192,"colonia_place_count":4,"colonia_avg_rating":3.65,"colonia_avg_traffic":14.0},{"id_colonia":162,"colonia_place_count":1,"colonia_avg_rating":3.5,"colonia_avg_traffic":37.0},{"id_colonia":2889,"colonia_place_count":296,"colonia_avg_rating":4.13,"colonia_avg_traffic":2376.0},{"id_colonia":3319,"colonia_place_count":1,"colonia_avg_rating":4.9,"colonia_avg_traffic":628.0},{"id_colonia":2914,"colonia_place_count":1,"colonia_avg_rating":2.5,"colonia_avg_traffic":8.0},{"id_colonia":1676,"colonia_place_count":10,"colonia_avg_rating":4.3,"colonia_avg_traffic":198.0},{"id_colonia":1034,"colonia_place_count":16,"colonia_avg_rating":4.26,"colonia_avg_traffic":615.0},{"id_colonia":3411,"colonia_place_count":2,"colonia_avg_rating":4.45,"colonia_avg_traffic":108.0},{"id_colonia":3423,"colonia_place_count":1,"colonia_avg_rating":4.0,"colonia_avg_traffic":11453.0},{"id_colonia":1386,"colonia_place_count":3,"colonia_avg_rating":4.23,"colonia_avg_traffic":159.0},{"id_colonia":751,"colonia_place_count":1,"colonia_avg_rating":4.4,"colonia_avg_traffic":68.0},{"id_colonia":2408,"colonia_place_count":32,"colonia_avg_rating":4.0,"colonia_avg_traffic":128.0},{"id_colonia":1903,"colonia_place_count":1,"colonia_avg_rating":3.0,"colonia_avg_traffic":3.0},{"id_colonia":2141,"colonia_place_count":3,"colonia_avg_rating":3.93,"colonia_avg_traffic":415.0},{"id_colonia":323,"colonia_place_count":4,"colonia_avg_rating":4.43,"colonia_avg_traffic":343.0},{"id_colonia":3273,"colonia_place_count":3,"colonia_avg_rating":4.27,"colonia_avg_traffic":13.0},{"id_colonia":818,"colonia_place_count":1,"colonia_avg_rating":4.3,"colonia_avg_traffic":3.0},{"id_colonia":613,"colonia_place_count":1,"colonia_avg_rating":4.2,"colonia_avg_traffic":89.0},{"id_colonia":1042,"colonia_place_count":12,"colonia_avg_rating":4.14,"colonia_avg_traffic":114.0},{"id_colonia":268,"colonia_place_count":1,"colonia_avg_rating":4.5,"colonia_avg_traffic":8.0},{"id_colonia":2966,"colonia_place_count":1,"colonia_avg_rating":4.9,"colonia_avg_traffic":9.0},{"id_colonia":2371,"colonia_place_count":1,"colonia_avg_rating":4.1,"colonia_avg_traffic":13.0},{"id_colonia":1404,"colonia_place_count":2,"colonia_avg_rating":4.65,"colonia_avg_traffic":19.0},{"id_colonia":3195,"colonia_place_count":19,"colonia_avg_rating":4.01,"colonia_avg_traffic":1289.0},{"id_colonia":1545,"colonia_place_count":3,"colonia_avg_rating":3.47,"colonia_avg_traffic":166.0},{"id_colonia":3151,"colonia_place_count":61,"colonia_avg_rating":3.89,"colonia_avg_traffic":177.0},{"id_colonia":3578,"colonia_place_count":1,"colonia_avg_rating":3.7,"colonia_avg_traffic":294.0},{"id_colonia":2908,"colonia_place_count":9,"colonia_avg_rating":4.24,"colonia_avg_traffic":838.0},{"id_colonia":3576,"colonia_place_count":1,"colonia_avg_rating":4.3,"colonia_avg_traffic":123.0},{"id_colonia":685,"colonia_place_count":1,"colonia_avg_rating":5.0,"colonia_avg_traffic":3.0},{"id_colonia":3365,"colonia_place_count":2,"colonia_avg_rating":4.3,"colonia_avg_traffic":99.0},{"id_colonia":2671,"colonia_place_count":54,"colonia_avg_rating":4.01,"colonia_avg_traffic":81.0},{"id_colonia":2926,"colonia_place_count":3,"colonia_avg_rating":4.57,"colonia_avg_traffic":17.0},{"id_colonia":1379,"colonia_place_count":4,"colonia_avg_rating":3.8,"colonia_avg_traffic":1046.0},{"id_colonia":1925,"colonia_place_count":1,"colonia_avg_rating":4.0,"colonia_avg_traffic":1.0},{"id_colonia":3620,"colonia_place_count":1,"colonia_avg_rating":4.2,"colonia_avg_traffic":155.0},{"id_colonia":1390,"colonia_place_count":5,"colonia_avg_rating":4.0,"colonia_avg_traffic":6262.0},{"id_colonia":3506,"colonia_place_count":6,"colonia_avg_rating":3.78,"colonia_avg_traffic":199.0},{"id_colonia":3115,"colonia_place_count":18,"colonia_avg_rating":3.82,"colonia_avg_traffic":1037.0},{"id_colonia":17,"colonia_place_count":3,"colonia_avg_rating":4.1,"colonia_avg_traffic":295.0},{"id_colonia":212,"colonia_place_count":1,"colonia_avg_rating":3.5,"colonia_avg_traffic":4.0},{"id_colonia":1380,"colonia_place_count":8,"colonia_avg_rating":4.06,"colonia_avg_traffic":948.0},{"id_colonia":404,"colonia_place_count":1,"colonia_avg_rating":4.4,"colonia_avg_traffic":117.0},{"id_colonia":720,"colonia_place_count":3,"colonia_avg_rating":4.27,"colonia_avg_traffic":4.0},{"id_colonia":917,"colonia_place_count":21,"colonia_avg_rating":4.0,"colonia_avg_traffic":252.0},{"id_colonia":3731,"colonia_place_count":1,"colonia_avg_rating":4.7,"colonia_avg_traffic":14.0},{"id_colonia":2913,"colonia_place_count":2,"colonia_avg_rating":4.3,"colonia_avg_traffic":50.0},{"id_colonia":489,"colonia_place_count":2,"colonia_avg_rating":4.45,"colonia_avg_traffic":680.0},{"id_colonia":3286,"colonia_place_count":9,"colonia_avg_rating":4.28,"colonia_avg_traffic":157.0},{"id_colonia":2909,"colonia_place_count":7,"colonia_avg_rating":3.71,"colonia_avg_traffic":800.0},{"id_colonia":1000,"colonia_place_count":1,"colonia_avg_rating":5.0,"colonia_avg_traffic":2.0},{"id_colonia":616,"colonia_place_count":17,"colonia_avg_rating":4.49,"colonia_avg_traffic":27.0},{"id_colonia":2282,"colonia_place_count":2,"colonia_avg_rating":4.75,"colonia_avg_traffic":6.0},{"id_colonia":1211,"colonia_place_count":2,"colonia_avg_rating":4.3,"colonia_avg_traffic":16876.0},{"id_colonia":706,"colonia_place_count":27,"colonia_avg_rating":3.93,"colonia_avg_traffic":91.0},{"id_colonia":2139,"colonia_place_count":2,"colonia_avg_rating":4.05,"colonia_avg_traffic":47.0},{"id_colonia":666,"colonia_place_count":1,"colonia_avg_rating":5.0,"colonia_avg_traffic":1113.0},{"id_colonia":882,"colonia_place_count":1,"colonia_avg_rating":4.1,"colonia_avg_traffic":8219.0},{"id_colonia":958,"colonia_place_count":2,"colonia_avg_rating":3.6,"colonia_avg_traffic":20.0},{"id_colonia":1590,"colonia_place_count":12,"colonia_avg_rating":4.2,"colonia_avg_traffic":27.0},{"id_colonia":669,"colonia_place_count":1,"colonia_avg_rating":4.0,"colonia_avg_traffic":4.0},{"id_colonia":1103,"colonia_place_count":1,"colonia_avg_rating":4.0,"colonia_avg_traffic":165.0},{"id_colonia":1302,"colonia_place_count":3,"colonia_avg_rating":4.47,"colonia_avg_traffic":7.0},{"id_colonia":3450,"colonia_place_count":2,"colonia_avg_rating":3.9,"colonia_avg_traffic":225.0},{"id_colonia":3260,"colonia_place_count":1,"colonia_avg_rating":3.6,"colonia_avg_traffic":42.0},{"id_colonia":352,"colonia_place_count":5,"colonia_avg_rating":4.28,"colonia_avg_traffic":8.0},{"id_colonia":3353,"colonia_place_count":4,"colonia_avg_rating":4.28,"colonia_avg_traffic":126.0},{"id_colonia":3006,"colonia_place_count":34,"colonia_avg_rating":4.16,"colonia_avg_traffic":782.0},{"id_colonia":1288,"colonia_place_count":2,"colonia_avg_rating":3.95,"colonia_avg_traffic":100.0},{"id_colonia":1760,"colonia_place_count":1,"colonia_avg_rating":2.1,"colonia_avg_traffic":156.0},{"id_colonia":594,"colonia_place_count":1,"colonia_avg_rating":3.6,"colonia_avg_traffic":25.0},{"id_colonia":2048,"colonia_place_count":1,"colonia_avg_rating":4.0,"colonia_avg_traffic":93.0},{"id_colonia":3376,"colonia_place_count":1,"colonia_avg_rating":4.2,"colonia_avg_traffic":5468.0},{"id_colonia":265,"colonia_place_count":2,"colonia_avg_rating":4.4,"colonia_avg_traffic":29.0},{"id_colonia":3024,"colonia_place_count":1,"colonia_avg_rating":4.8,"colonia_avg_traffic":6.0},{"id_colonia":1709,"colonia_place_count":4,"colonia_avg_rating":4.65,"colonia_avg_traffic":35.0},{"id_colonia":968,"colonia_place_count":39,"colonia_avg_rating":4.18,"colonia_avg_traffic":3351.0},{"id_colonia":326,"colonia_place_count":2,"colonia_avg_rating":3.25,"colonia_avg_traffic":38.0},{"id_colonia":1939,"colonia_place_count":546,"colonia_avg_rating":4.0,"colonia_avg_traffic":352.0},{"id_colonia":1822,"colonia_place_count":257,"colonia_avg_rating":4.18,"colonia_avg_traffic":334.0},{"id_colonia":150,"colonia_place_count":1,"colonia_avg_rating":3.7,"colonia_avg_traffic":2420.0},{"id_colonia":3504,"colonia_place_count":1,"colonia_avg_rating":5.0,"colonia_avg_traffic":16.0},{"id_colonia":835,"colonia_place_count":1,"colonia_avg_rating":5.0,"colonia_avg_traffic":1.0},{"id_colonia":25,"colonia_place_count":8,"colonia_avg_rating":4.14,"colonia_avg_traffic":949.0},{"id_colonia":2664,"colonia_place_count":1,"colonia_avg_rating":5.0,"colonia_avg_traffic":13.0},{"id_colonia":3491,"colonia_place_count":2,"colonia_avg_rating":3.95,"colonia_avg_traffic":14.0},{"id_colonia":923,"colonia_place_count":2,"colonia_avg_rating":4.55,"colonia_avg_traffic":60.0},{"id_colonia":1320,"colonia_place_count":3,"colonia_avg_rating":4.33,"colonia_avg_traffic":4.0},{"id_colonia":1867,"colonia_place_count":8,"colonia_avg_rating":3.91,"colonia_avg_traffic":36.0},{"id_colonia":3795,"colonia_place_count":22,"colonia_avg_rating":4.11,"colonia_avg_traffic":34.0},{"id_colonia":64,"colonia_place_count":1,"colonia_avg_rating":3.4,"colonia_avg_traffic":5.0},{"id_colonia":1853,"colonia_place_count":7,"colonia_avg_rating":3.97,"colonia_avg_traffic":114.0},{"id_colonia":2714,"colonia_place_count":1,"colonia_avg_rating":2.3,"colonia_avg_traffic":102.0},{"id_colonia":3276,"colonia_place_count":19,"colonia_avg_rating":4.42,"colonia_avg_traffic":11.0},{"id_colonia":148,"colonia_place_count":19,"colonia_avg_rating":4.07,"colonia_avg_traffic":208.0}]